Workbook

Sheet Instructions
A1: OpenAlex R2+A1 Baseline — Blind Human Audit
A3: 目的：各 OpenAlex record が、指定された target literary work を実際に参照しているかを、LLM判定を見ずに監査します。
A5: 判定 | B5: 意味 | D5: Review rules
A6: VALID_TARGET_REFERENCE | B6: 表示された情報から、対象作品への参照が十分に確認できる。 | D6: 1 | E6: Web検索はしない。
A7: INVALID_TARGET_REFERENCE | B7: 表示された情報から、対象作品への参照ではないと確認できる。 | D7: 2 | E7: LLMのcandidate-level判定・sampling stratum・risk featureは見ない。
A8: UNCERTAIN | B8: 表示された情報だけでは valid / invalid を確実に決められない。 | D8: 3 | E8: substantive analysis の有無ではなく、target workへの参照そのものを判定する。
D9: 4 | E9: primary text / bibliography / review / brief mention でも、target workを実際に指せばVALIDになり得る。
D10: 5 | E10: INVALID / UNCERTAIN は Reviewer note に短い根拠を書く。
A12: Batch | B12: Completed | C12: VALID | D12: INVALID | E12: UNCERTAIN | F12: Total
A13: Audit 01 | B13: =SUM(C13:E13) -> 25 | C13: =COUNTIF('Audit 01'!I6:I30,"VALID_TARGET_REFERENCE") -> 23 | D13: =COUNTIF('Audit 01'!I6:I30,"INVALID_TARGET_REFERENCE") -> 2 | E13: =COUNTIF('Audit 01'!I6:I30,"UNCERTAIN") -> 0 | F13: 25
A14: Audit 02 | B14: =SUM(C14:E14) -> 25 | C14: =COUNTIF('Audit 02'!I6:I30,"VALID_TARGET_REFERENCE") -> 23 | D14: =COUNTIF('Audit 02'!I6:I30,"INVALID_TARGET_REFERENCE") -> 2 | E14: =COUNTIF('Audit 02'!I6:I30,"UNCERTAIN") -> 0 | F14: 25
A15: Audit 03 | B15: =SUM(C15:E15) -> 25 | C15: =COUNTIF('Audit 03'!I6:I30,"VALID_TARGET_REFERENCE") -> 21 | D15: =COUNTIF('Audit 03'!I6:I30,"INVALID_TARGET_REFERENCE") -> 4 | E15: =COUNTIF('Audit 03'!I6:I30,"UNCERTAIN") -> 0 | F15: 25
A16: Audit 04 | B16: =SUM(C16:E16) -> 25 | C16: =COUNTIF('Audit 04'!I6:I30,"VALID_TARGET_REFERENCE") -> 23 | D16: =COUNTIF('Audit 04'!I6:I30,"INVALID_TARGET_REFERENCE") -> 0 | E16: =COUNTIF('Audit 04'!I6:I30,"UNCERTAIN") -> 2 | F16: 25
A17: Audit 05 | B17: =SUM(C17:E17) -> 25 | C17: =COUNTIF('Audit 05'!I6:I30,"VALID_TARGET_REFERENCE") -> 21 | D17: =COUNTIF('Audit 05'!I6:I30,"INVALID_TARGET_REFERENCE") -> 2 | E17: =COUNTIF('Audit 05'!I6:I30,"UNCERTAIN") -> 2 | F17: 25
A18: Audit 06 | B18: =SUM(C18:E18) -> 25 | C18: =COUNTIF('Audit 06'!I6:I30,"VALID_TARGET_REFERENCE") -> 22 | D18: =COUNTIF('Audit 06'!I6:I30,"INVALID_TARGET_REFERENCE") -> 3 | E18: =COUNTIF('Audit 06'!I6:I30,"UNCERTAIN") -> 0 | F18: 25
A19: TOTAL | B19: =SUM(B13:B18) -> 150 | C19: =SUM(C13:C18) -> 133 | D19: =SUM(D13:D18) -> 13 | E19: =SUM(E13:E18) -> 4 | F19: 150
A22: Judgment | B22: Reason code | C22: Meaning
A23: VALID | B23: DIRECT_TARGET_REFERENCE | C23: Explicit title/work + author linkage identifies the target.
A24: VALID | B24: VALID_TITLE_VARIANT | C24: Supported alternate/shortened/translated title denotes the same target.
A25: VALID | B25: VALID_CONTEXTUAL_REFERENCE | C25: Context sufficiently identifies the target without direct bibliographic naming.
A26: INVALID | B26: TITLE_COLLISION_DIFFERENT_WORK | C26: Matching title denotes a different work.
A27: INVALID | B27: GENERIC_OR_LEXICAL_TITLE_USE | C27: Matched expression is ordinary/generic language, not the target title.
A28: INVALID | B28: AUTHOR_COLLISION_DIFFERENT_PERSON | C28: Matched author name denotes another person.
A29: INVALID | B29: TITLE_AUTHOR_UNLINKED_COOCCURRENCE | C29: Title expression and author appear but are not semantically linked as the target.
A30: INVALID | B30: WRONG_WORK_SAME_AUTHOR | C30: A different work by the same author is identified.
A31: INVALID | B31: ALIAS_NOT_TARGET_EQUIVALENT | C31: The apparent target/title relationship is not the same underlying work.
A32: INVALID | B32: METADATA_TEXT_ARTIFACT | C32: A metadata/text artifact causes the false match.
A33: INVALID | B33: OTHER | C33: Established invalidity outside the listed reasons; explain in note.
... A35: UNCERTAIN | B35: AMBIGUOUS_TARGET_REFERENCE | C35: Specific competing work identities remain unresolved.
A38: Provenance / safeguards
A39: Frozen human-audit sample | B39: 150 candidates / 90 project works / 6 batches × 25
A40: Repository branch | B40: kakenc-integration-20260927
A41: Frozen packet commit | B41: 6260c82f9883762b46a3b4384e70d037278ac886
A42: Blinding | B42: LLM candidate judgments, LLM strata, analysis weights, and retrieval-risk features are absent from this workbook.

Sheet Lists
A1: Judgment | B1: Confidence | C1: Reason code | E1: Do not edit — validation source lists.
A2: VALID_TARGET_REFERENCE | B2: HIGH | C2: DIRECT_TARGET_REFERENCE
A3: INVALID_TARGET_REFERENCE | B3: MEDIUM | C3: VALID_TITLE_VARIANT
A4: UNCERTAIN | B4: LOW | C4: VALID_CONTEXTUAL_REFERENCE
C5: TITLE_COLLISION_DIFFERENT_WORK
C6: GENERIC_OR_LEXICAL_TITLE_USE
C7: AUTHOR_COLLISION_DIFFERENT_PERSON
C8: TITLE_AUTHOR_UNLINKED_COOCCURRENCE
C9: WRONG_WORK_SAME_AUTHOR
C10: ALIAS_NOT_TARGET_EQUIVALENT
C11: METADATA_TEXT_ARTIFACT
C12: OTHER
C13: INSUFFICIENT_CONTEXT
C14: AMBIGUOUS_TARGET_REFERENCE

Sheet Audit 01
A1: OpenAlex R2+A1 Blind Human Audit — R2A1A01
A2: 判定対象：OpenAlex record が target literary work を本当に参照しているか。LLM判定・sampling stratum・risk featureは非表示です。Web検索はしません。
A4: 入力欄 → | I4: Judgment | J4: Confidence | K4: Reason | L4: Reviewer note
A5: Review # | B5: Target title | C5: Target author | D5: OpenAlex record title | E5: OpenAlex abstract | F5: Year | G5: Publication date | H5: DOI | I5: Judgment | J5: Confidence | K5: Reason | L5: Reviewer note | M5: Candidate ID | N5: Project Work ID | O5: OpenAlex Work ID
A6: 1 | B6: Henry James | C6: Henry James | D6: Naming the father: legacies, genealogies, and explorations of fatherhood in modern and contemporary literature | E6: chapter 1 Acknowledgments chapter 2 Introduction: Naming the Dead chapter 3 Part One: in Memory. Business of Mourning chapter 4 Two Fingers of Chat chapter 5 Culture of My Childhood. Part Two: Fathers in Ethnic Culture. Performative Fathers and the Inessential Macho: Fatherhood in Contemporary Latino/Latina Literature chapter 6 Negations and Subversions of Paternal Authorities in Glissant's Fictional Works (Le Quatrime Sicle, La Case du commandeur, Tout-monde) chapter 7 Holy and Unholy Ghosts: Legacy of the in the Plays of August Wilson. Part Three: Fathers and Daughters. Legacy of The Unspeakable Father in Henry James's Wings of the Dove chapter 8 Generating Alternative Representations of Fatherhood: Anzia Yezierska and Dorothy Canfield Fisher's Narrative Spaces for Male Others chapter 9 Daughters of Memory: Modernist Poet as Father. Part Four: Beyond the Father. Oedipus and the Modernist Aesthetic: Reconceiving the Social in Rebecca West's Return of the Soldier chapter 10 Naming the Father: Genealogy, Spectacle, and Jack Nicholson in Going Native chapter 11 Original Chaos Restored: Paternal Fictions in William S. Burroughs chapter 12 Works Cited chapter 13 Index | F6: 2001.0 | G6: 2001-01-01 | H6: https://doi.org/10.5860/choice.38-2616 | I6: VALID_TARGET_REFERENCE | J6: HIGH | K6: DIRECT_TARGET_REFERENCE | L6: 著者名ターゲット：Wings of the Dove を扱う章あり | M6: OABASEV1_fff0b83e8226a6c7 | N6: W000014024 | O6: W2953498596
A7: 2 | B7: The years | C7: Virginia Woolf | D7: Beyond the Five Towns: a re-evaluation of Arnold Bennett | E7: ‘I have a great deal to say, and I mean to say it. As for my work being taken seriously, we shall see about that’. Arnold Bennett, 1909 (Bennett, letter to Pinker dated 17 May 1909, in Letters, Vol. I, p. 123.) Arnold Bennett occupies a somewhat anomalous position as an Edwardian realist in a century dominated by modernist aesthetics. Pigeonholed by critics who have tended to adopt an overly formalist approach when considering his fiction, Bennett’s critical acclaim has predominantly been restricted to his Five Towns novels and has been advocated through readings which arrogate to him a slavish homage to nineteenth-century French naturalism and a quasi-documentary representation of particular locales. This dissertation aims to challenge Bennett’s categorisation as a merely provincial author, and as an Edwardian deserving of the canonical segregation initially proposed by Virginia Woolf, which separates his work from – and subordinates it to – that of his early twentieth-century or early Modernist contemporaries. To this end, I will demonstrate that Bennett was in fact, readily incorporating early twentieth-century themes and techniques, and actively engaging with various aspects of individual, social and national politics in comparable ways to other Modernists. I will also contend – contrary to critics who have regarded the war as having killed Bennett’s creativity – that the war occasioned a shift in Bennett’s agenda that, though not appreciated in his time or in the years after his death, is now in need of re-evaluation. With respect to methodology, this dissertation contextualises Bennett’s artistic strategies in light of early twentieth-century aesthetic concerns, and it demonstrates that his prose techniques serve social and/or political purposes. The thesis is divided into three chapters, each of which explores a stage of Bennett’s literary career. Chapter I covers 1898, the year of publication for Bennett’s first novel, The Man from the North, to 1913, also analysing A Great Man (1904) and Buried Alive (1908). Chapter II attends to Bennett’s fictional and non-fictional writings of the War years, including The Roll-Call (1919) – which begins in 1901 and culminates in 1914 – Liberty (1914), and Over There (1915). Chapter III examines Bennett’s writing from 1919 onwards, focusing on three novels: Riceyman Steps (1923), Lord Raingo (1926), and Accident (1929). | F7: 2020.0 | G7: 2020-03-01 | I7: INVALID_TARGET_REFERENCE | J7: HIGH | K7: GENERIC_OR_LEXICAL_TITLE_USE | L7: Woolfは言及されるが「The Years」は未言及。"the years after his death"は一般語 | M7: OABASEV1_5b3983b28a67c900 | N7: W000018226 | O7: W6989607625
A8: 3 | B8: Santa | C8: Federico Gamboa | D8: Subversión del mito de Ciudad de México como Nueva Jerusalén en Santa de Gamboa | E8: Santa (1903) de Federico Gamboa se publica durante el regimen dictatorial de Porfirio Diaz para cuestionar, por un lado, sus dos maximas de “orden y progreso”, al tiempo que para analizar a sociedad de su tiempo y evolucion historica e ideologa de Iglesia colonial en Nueva Espana. Esta Iglesia transculturizo el mito utopico de Jerusalen en Ciudad de Mexico para propagar la grandeza mexicana y, por extension, del Imperio colonial espanol. Santa-prostituta, protagonista de novela y alegoria de Ciudad de Mexico, subvierte esta ideologia y sufre los estragos de una sociedad capitalista en ciernes al metaforizar corrupcion y transformacion de Ciudad de Mexico del Porfiriato. Este se nutrio de los ideales utopicos coloniales y se propuso abrir el pais a las inversiones extranjeras y al progreso. Gamboa coloca a Santa en el tiempo presente y pasado de ideologia colonial y eclesiastica que, a raiz sobre todo de aparicion guadalupana en 1531, busco evangelizar las tierras de Nueva Espana y en especial Ciudad de Mexico con los dictados del pensamiento utopico renacentista. | F8: 2014.0 | G8: 2014-11-27 | I8: VALID_TARGET_REFERENCE | J8: HIGH | K8: DIRECT_TARGET_REFERENCE | M8: OABASEV1_089588d91e7b4ae8 | N8: W000009285 | O8: W1415955523
A9: 4 | B9: A Clergyman's Daughter | C9: George Orwell | D9: The lasting in the ephemeral: assessing George Orwell’s As I Please columns | E9: George Orwell, author of the world famous Animal Farm (1945) and Nineteen Eighty-Four (1949), was also one of the greatest journalists of the last century. Born Eric Arthur Blair in Motihari, Bengal, in 1903, he won a scholarship to Eton but in 1921 left the college 138th out of 167 candidates in final-year exams. Confounding the expectations of his family, he sailed for Rangoon, Burma, to become a probationary assistant district superintendent of the Imperial Police. But he grew disillusioned with British imperialism and in 1927 resigned ‘on medical grounds’. That winter he went ‘down and out’ in London’s East End and the following year moved to a cheap hotel in Paris. He adopted the pseudonym George Orwell in November 1932, and Down and Out in Paris and London was published during the following year. The novels Burmese Days (1935), A Clergyman’s Daughter (1935) and Keep the Aspidistra Flying (1936) followed in quick succession. In 1936 he travelled through northern England, the West Midlands, Lancashire and Yorkshire researching the working class, and in December delivered the manuscript of The Road to Wigan Pier before leaving for Spain, which was in the grip of civil war. Here he fought for the Republicans against the fascists led by General Franco and was wounded, his experiences (and his conversion to socialism) being captured in Homage to Catalonia (1938). After two unhappy years working for the BBC’s Eastern Service, in February 1943 he became literary editor of Tribune, writing the weekly As I Please column. In 1945 he served as a war correspondent on the Continent for David Astor’s Observer. The same year also saw the publication of Animal Farm, which secured massive sales in Britain and the United States, and he began spending part of every 12 months in a cottage on the remote Scottish island of Jura, Inner Hebrides. While his health continued to deteriorate he worked on completing Nineteen Eighty-Four. He died in 1950 aged just 46, soon after marrying his second wife, Sonia. | F9: 2007.0 | G9: 2007-09-14 | H9: https://doi.org/10.4324/9780203939765-12 | I9: VALID_TARGET_REFERENCE | J9: HIGH | K9: DIRECT_TARGET_REFERENCE | L9: 書誌的な簡潔な言及（刊行年付き） | M9: OABASEV1_e8ef18a38ee80227 | N9: W000001625 | O9: W2282398063
A10: 5 | B10: Galen | C10: Galen | D10: Cerebral Venous Thrombosis Associated with COVID-19 | E10: Despite the severity of coronavirus disease 2019 (COVID-19) being more frequently related to acute respiratory distress syndrome and acute cardiac and renal injuries, thromboembolic events have been increasingly reported. We report a unique series of young patients with COVID-19 presenting with cerebral venous system thrombosis. Three patients younger than 41 years of age with confirmed Severe Acute Respiratory Syndrome coronavirus 2 (SARS-Cov-2) infection had neurologic findings related to cerebral venous thrombosis. They were admitted during the short period of 10 days between March and April 2020 and were managed in an academic institution in a large city. One patient had thrombosis in both the superficial and deep systems; another had involvement of the straight sinus, vein of Galen, and internal cerebral veins; and a third patient had thrombosis of the deep medullary veins. Two patients presented with hemorrhagic venous infarcts. The median time from COVID-19 symptoms to a thrombotic event was 7 days (range, 2-7 days). One patient was diagnosed with new-onset diabetic ketoacidosis, and another one used oral contraceptive pills. Two patients were managed with both hydroxychloroquine and azithromycin; one was treated with lopinavir-ritonavir. All patients had a fatal outcome. Severe and potentially fatal deep cerebral thrombosis may complicate the initial clinical presentation of COVID-19. We urge awareness of this atypical manifestation. | F10: 2020.0 | G10: 2020-05-20 | H10: https://doi.org/10.3174/ajnr.a6644 | I10: INVALID_TARGET_REFERENCE | J10: HIGH | K10: GENERIC_OR_LEXICAL_TITLE_USE | L10: "vein of Galen"（解剖学上の名祖）。著作への参照ではない | M10: OABASEV1_1dfbbf947e5898cd | N10: W000031472 | O10: W3027462748
A11: 6 | B11: Marie de France | C11: Marie de France | D11: Arthurian Literature by Women ed. by Alan Lupack and Barbara Tepa Lupack (review) | E11: REVIEWS115 scriptural exegesis. The author's appreciation for the Anglo-Saxon poet and his craft is everywhere palpable. Yet this is no blind admiration, but rather a feeling that has grown over many years of teaching and writing, reflecting on the nature of artistic creation and the deep meaning of the words of Beowulf. LEO CARRUTHF.RS Université de Paris-Sorbonne alan lupack and barbara tepa lupack, eds., Arthurian Literature by Women. Garland Reference Library of the Humanities 2137. New York: Garland, 1999. Pp. xiii, 382. isbn: 0-8153-3305-6 (hbk); 0-8153-3483-4 (pbk). $19.95. This anthology emphasizes Arthurian works by nineteenth- and twentieth-century women authors, although it also includes Marie de France's two Arthurian lais (twelfth century) and Lady Charlotte Guest's 1849 translation ofthe medieval Welsh tale, 'The Lady ofthe Fountain.' The intended audience for the collection is explicitly one already familiar with the writing ofsuch modern women writers ofArthurian subjects as Vera Chapman, Mary Stewart, Rosemary Sutcliff, Jane Yolen, Katherine Paterson, Fay Sampson, Gillian Bradshaw, Persia Woolley, and Marion Zimmer Bradley, and their writing is thus not represented. In fact, the names of the great majority ofwriters in Arthurian Literature by Women will probably be unfamiliar to all but zealous Arthurianists, preferably with access to works long out ofprint. This is as the editors have anticipated, however, for they hope 'to explore that rich but forgotten tradition' (xi), a phrase that in part provides the title oftheir introduction. The earliest modern work reprinted hete is Anne Bannerman's 'The Prophecy of Merlin' (1802), followed by Letitia Elizabeth Landon's A Legend ofTintagel Castle' (1833) and the anonymous—the author signs merely as a 'daughter of Eve'—'The YIIe Cut Manteir (1844), a story that can be traced to the Middle Ages. Thirteen other works date from the second halfofthe nineteenth century. To note just three: the selections by Elizabeth Stuart Phelps re-create Galahad, Elaine/The Lady of Shalott, and Guenevere as poor folk living in 'realistic' squalor, presented with the heightened pathos such a setting can allow; Dinah Maria Mulock Craik's Avillion; Or, the Happy Isles features the enfeebled Wilfred Mayer and his devoted wife Lilias Hay; their encounter, during a sea voyage, with a German physician and his magic medicine sends Mayer into a lengthy but curative dream that includes both Greek mythological and Arthurian personae; and the scholar Jessie Weston is represented by a poem, 'Knights of King Arthur's Court,' written in 1896. A concentration ofselections from the period between 1901-1931 includes Martha Kinross's much-admired drama 'Tristram and Isoult,' two poems by Sara Teasdale, Edna St. Vincent Millay's 'Elaine,' and Dorothy Parker's 'Guinevere at Her Fireside' and 'Iseult of Brittany.' Conceivably less known are the short poems by Grace Constant Lounsbery, Sophie Jewett, Helen Hay Whitney, Elizabeth Colwell, and Aline Kilmer. Annie Fellows Johnston's prose tale, 'Keeping Tryst: ATaIe of King Arthur's Time,' is a children's story (but there is nothing new in the blurring of borders in much modern Arthurian composition between stories for children or Il6ARTHURIANA young adults and those for older readers). Two selections, Valerie Nieman's intriguing 'The Naming of the Lost' (1989) and four Guenevere poems by Wendy Mnookin (1991) close the volume. Readers will appreciate the generous number of works that this anthology provides, as well as the valuable service it performs by making available otherwise hard-to-get writing. A spot check of selections against first editions inspires confidence in the editors' care in transcription. Some aspects ofpresentation, however, may prove baffling. For editors, choosing from an array of material is always a daunting task, and focusing on the worthybut -forgotten is an unimpeachable aim. But it is surprising to read that Marie de France's 'Lanval' (with all due respect for Norris Lacy's translation) or 'The Lady of the Fountain' are forgotten, given that they are available elsewhere in inexpensive editions (a translation of 'Lanval' is even posted on the Net) and often used in college courses. Similarly, Wendy Mnookin's poetry, composed within the last decade, isn't old enough to have been forgotten, nor indeed is it... | F11: 2000.0 | G11: 2000-06-01 | H11: https://doi.org/10.1353/art.2000.0018 | I11: VALID_TARGET_REFERENCE | J11: HIGH | K11: DIRECT_TARGET_REFERENCE | L11: Marie de FranceのLanval等アーサー王レーを収録・論評 | M11: OABASEV1_40bebf73fdd0df4a | N11: W000000860 | O11: W2023772851
A12: 7 | B12: Edgar Allan Poe | C12: Edgar Allan Poe | D12: Padre Brown e Chesterton | E12: Este artigo propõe uma análise dos romances policiais de G. K. Chesterton, com ênfase no personagem Padre Brown, em diálogo com a história do gênero policial e seu contexto social. A partir da reflexão de Borges, que posiciona Chesterton como herdeiro de Edgar Allan Poe por unir elementos fantásticos a soluções racionais, discutimos como suas narrativas policiais interagem com o surgimento da polícia moderna. Neste percurso, autores como Todorov, Carpeaux e Ortega y Gasset são referências para pensar a história do romance policial e a sua relação com a sociedade. Com base nas reflexões propostas neste artigo, conclui-se que Chesterton oferece uma crítica à modernidade, não como uma decadência, mas como uma condição a ser desafiada, evocando um perfil quixotesco diante do mundo moderno. | F12: 2025.0 | G12: 2025-08-02 | H12: https://doi.org/10.12660/rm.v17n27.2025.93039 | I12: VALID_TARGET_REFERENCE | J12: MEDIUM | K12: VALID_CONTEXTUAL_REFERENCE | L12: 著者名ターゲット：Chestertonを「Poeの後継者」とする文学史的言及のみ | M12: OABASEV1_8637292cb4dcfc72 | N12: W000018534 | O12: W4415819236
A13: 8 | B13: Heart of Darkness | C13: Joseph Conrad | D13: Jack London's Heart of Darkness | E13: ALTHOUGH there are certain obvious similarities in the fiction of Jack London and Joseph Conrad-both wrote tales of the sea well stories set in exotic lands, and frequently both peopled their fiction with rough characters engaged in violent action-Conrad's different emphasis, surer craftsmanship and more profound insight into the psychological motivations of his characters have made these similarities seem relatively inconsequential. London is often, even within the same book, an exponent of the cult of raw meat and red blood and a political expounder using fiction a means of advancing the doctrines of socialism. This blatant dichotomy is in obvious contrast to Conrad's characteristically subtle investigations of states of mind. Conrad himself bridled at being regarded as literarily a sort of Jack London: | F13: 1958.0 | G13: 1958-01-01 | H13: https://doi.org/10.2307/2710175 | I13: VALID_TARGET_REFERENCE | J13: HIGH | K13: VALID_CONTEXTUAL_REFERENCE | L13: 題名がConradの作品を援用し、本文でもConradを比較対象として扱う | M13: OABASEV1_949e657f2edb4f91 | N13: W000014272 | O13: W2313439067
A14: 9 | B14: The Road | C14: Jack London | D14: Jack London by Kenneth K. Brandt | E14: Reviewed by: Jack London by Kenneth K. Brandt Earle Labor Kenneth K. Brandt, Jack London. Liverpool: Liverpool UP, 2018. 149 pp. Cloth, $80; paper, $29.95. "Multum in Parvo" would be an appropriate title for this review. Seldom have I read a scholarly book that provided so much useful content in so few pages. In view of Kenneth Brandt's established position in the world of Jack London, I'm hardly surprised: executive coordinator of the Jack London Society and editor of The Call, the Society's official magazine; coeditor (with Jeanne C. Reesman) of Approaches to Teaching the Works of Jack London (2015); plus multiple shorter publications. Brandt states his approach in his opening chapter: "My study challenges the unexamined assumption that London's narrative accessibility consigns his work to thematic simplicity" (2). The following six chapters examine the extraordinary range of London's fiction from the Northland to the South Pacific with significant thematic variations in between: London's world-famous dystopian novel The Iron Heel, plus shorter Socialistic works like "Goliah" and "The Strength of the Strong"; the tragic consequences of "Individualism" in The Sea-Wolf and Martin Eden; the "compatibilistic" resolution of free will vs. determinism in The Road and The Star Rover. While selective rather than exhaustive, the representative works Brandt examines are truly exemplary. Beyond devoting considerable attention to popular novels like The Call of the Wild, White Fang, and The Sea-Wolf, he also includes careful readings of less-familiar works [End Page 452] like "Nam-Bok the Unveracious," "The Night-Born," "The House of Pride," "Mauki," "The Red One," and "The Water Baby." These last two stories are particularly noteworthy. Written during a period many critics have dismissed as creatively arid, they demonstrate the rich stylistic as well as thematic diversity of London's oeuvre. Brandt points out that while London was "adept at spinning a good yarn, [he] deliberately layered his fiction [and] ballasted his best stories with heftier motifs expressive of profounder implications" (15). Virtually unknown even by London fans for more than a half century, "The Red One" is arguably the most richly layered of all his stories. On one level it is an adventure tale about a modern scientist exploring the terra incognita of one of the Solomon Islands. Beneath this is the mystery of a sentient object apparently planted by some extraterrestrial force (think of Stanley Kubrick's 2001: A Space Odyssey). Deeper still, it dramatizes the universal human quest for the ultimate "Self" and "Truth." Finally, with its "wealth of allusions to the Bible and Greek mythology and English poetry," the story is comparable to T. S. Eliot's The Waste Land in suggesting "a viable repository of cultural knowledge that may serve to mitigate modernity's malaise" (120). "The Water Baby"—written shortly after his discovering C. G. Jung and less than two months before his death—is one of London's most revealing stories. Unlike most of his fiction, the physical action is minimal. Instead, tension is derived from a dialogue between two characters: John Lakana (London's Hawaiian name) and Kohokumu (Hawaiian for "tree of knowledge"). Lakana, a young Caucasian, as Brandt notes, "exemplifies Western rationality and the exhaustion of modernity" (121). Kohokumu, personifying Jung's archetypal figure of the Wise Old Man, is "an ebullient septuagenarian fully vitalized by the myth and lore of his native culture." In their argument, the elder character convincingly demonstrates that inner Truth transcends mere external Fact. "This I know," he tells Lakana, "as I grow old I seek less from the truth from without me, and find more of the truth from within me" (121). This remarkable story, his last, is eloquent testimony that London—ever the "seeker"—was still adventuring as he himself grew old. [End Page 453] Throughout this critical study Brandt undergirds his own interpretive insights with references to other significant scholarly works. The final chapter, "Coda: Literary Legacy and Scholarship"—surveying the growth of serious London scholarship during the past generation—effectively corrects the distorted image of a hack writer who made his fortune by commercializing popular dog stories. Contrary to this stereotype, London's international status as "a prominent writer and... | F14: 2020.0 | G14: 2020-01-01 | H14: https://doi.org/10.1353/wal.2020.0008 | I14: VALID_TARGET_REFERENCE | J14: HIGH | K14: DIRECT_TARGET_REFERENCE | M14: OABASEV1_edb5f6c48b0acfd7 | N14: W000026722 | O14: W3005009023
A15: 10 | B15: Galen | C15: Galen | D15: Greek Science - The Heart and the Vascular System in Ancient Greek Medicine from Alcmaeon to Galen. By C. R. S. Harris. Oxford: Clarendon Press: Oxford University Press, 1973. Pp. x + 474. £15.00. | E15: Greek Science - The Heart and the Vascular System in Ancient Greek Medicine from Alcmaeon to Galen. By C. R. S. Harris. Oxford: Clarendon Press: Oxford University Press, 1973. Pp. x + 474. £15.00. - Volume 7 Issue 2 | F15: 1974.0 | G15: 1974-07-01 | H15: https://doi.org/10.1017/s0007087400013236 | I15: VALID_TARGET_REFERENCE | J15: MEDIUM | K15: VALID_CONTEXTUAL_REFERENCE | L15: 著者名ターゲット：医学史書の題名中でGalen（医学著作者）に言及 | M15: OABASEV1_a0a4a13f8c9ccd49 | N15: W000031472 | O15: W1965933617
A16: 11 | B16: Ulysses | C16: James Joyce | D16: Beyond Borders: I.A.S.I.L. Essays on Modern Irish Writing (review) | E16: Reviewed by: Beyond Borders: I.A.S.I.L. Essays on Modern Irish Writing Walter Corbella (bio) Beyond Borders: I.A.S.I.L. Essays On Modern Irish Writing, edited by Neil Sammells . Bath: Sulis Press, 2004. 281 pp. $44.95. As historians and critics have frequently noted, Ireland is a deeply divided nation. Geographical, political, religious, and social boundaries have defined the Irish ethos and left an indelible mark in the work of Irish authors. This sense of division has determined, in multiple ways, the fragmentation that recurs as thematic component and stylistic device in their fiction. Beyond Borders recaptures these notions of boundaries, borders, and limits, as well as the associated concepts of transgression, crossing, and disruption as the organizing principles for the sixteen essays that form this collection. In "The Victorian Celt Stereotyped, Historicized and Imagined," Simon Trezise offers a historical and literary perspective on the phenomenon of stereotype formation. Focusing on nineteenth-century views of the Celts, particularly those of John Beddoe and Sophie Bryant, Trezise analyzes the interrelations between scientific bias and stereotypes.1 In opposition to the pseudoscientific notions of the Celt, he exposes the historical factors which led to the emergence of the Irish Celt as necessary racial and religious Other, stressing the attempts to combat those stereotypical views during the Irish Literary [End Page 398] Renaissance. In J. M. Synge's work, Trezise finds a more genuine, yet unsentimentalized, view of the Irish that arises from actual observation of, and interaction with, the people.2 This piece prepares the ground for the two subsequent essays, both of which foreground the relation between Padraic Pearse and W. B. Yeats. "Yeats and Pearse in Dialogue," by Robert Tracy, reads the Proclamation of the Irish Republic as political document, literary work, and response to Yeats's play Cathleen ni Houlihan.3 According to Tracy, through his use of imagery and his dramatic reading of the Proclamation, Pearse established a dialogue with Yeats that the latter would acknowledge and continue in his poem "Easter, 1916."4 Paul Murphy's "Yeats, Pearse and the Sublime Subaltern" lays emphasis on the ambiguity of Cathleen ni Houlihan. The play lends itself to two competing interpretations, both of which rely on the subordination of the archetypal "peasant" to national and class interests. By contrast, in Pearse's play The Singer, the idealized peasant assumes "oxymoronic status as the sublime subaltern" (48), which conceals his subordination.5 In Murphy's view, these plays exemplify the distinct approaches of "Anglo-Irish" and "Irish-Irish" ideologies in postcolonial contexts. It is hard to imagine that a conference on, or overview of, Irish literature would fail to include Yeats and James Joyce, and the International Association for the Study of Irish Literatures' collection proves no exception. Ellen Carol Jones's "Joyce and Dividing Lines" and Louis Armand's "Joycean Hypertext: Technology and the Word in Finnegans Wake" approach Joyce's work from the perspective of postcolonial and postmodern theory respectively. Jones's somewhat obscure reading of the "Oxen of the Sun" episode in Ulysses explores the uses of language in the negotiation of identities through the production of "hybrid writing" in an "in-between space" (57). In such a space, the subaltern can engage in acts of translation, transgression, and transcription. In reference to the transgressive use of translation, Jones wonders, "How does cultural translation as a tropic movement transform the heliotropics of a dominant culture, the heliopolitics of imperialism?" (58). This type of "cultural translation," she argues, appears as pastiche in "Oxen of the Sun" and serves the purposes of interrogating and fragmenting the dominant cultural paradigms. At the same time, the creation of hybrid language and writing attests to the miscegenation resulting from imperialism. Having acknowledged Jacques Derrida's and Jean-Michel Rabaté's essays on Finnegans Wake, Armand characterizes Joyce's text as a language-producing machine.6 He claims, "The desiring machine, miming the totalizing movement of an exegesis, or exe-genesis, approaches a topological relation to itself similar to that of the Cantorean paradox of the set of all sets" (73-74). This statement illustrates the ways in which the complexities of Armand's prose complicate his interpretation of... | F16: 2007.0 | G16: 2007-10-21 | H16: https://doi.org/10.1353/jjq.2007.0029 | I16: VALID_TARGET_REFERENCE | J16: HIGH | K16: DIRECT_TARGET_REFERENCE | L16: Ulysses "Oxen of the Sun"エピソードの論評 | M16: OABASEV1_15a44f295ac4a304 | N16: W000016985 | O16: W2067893208
A17: 12 | B17: Henry James | C17: Henry James | D17: Theme and its Embadiment in the Works of Henry James | F17: 1984.0 | G17: 1984-05-01 | I17: VALID_TARGET_REFERENCE | J17: HIGH | K17: DIRECT_TARGET_REFERENCE | M17: OABASEV1_b85d6b77c16fdc95 | N17: W000014024 | O17: W2342413711
A18: 13 | B18: D.H. Lawrence | C18: D. H. Lawrence | D18: Cult of spontaneity : D. H. Lawrence and occult | F18: 2006.0 | G18: 2006-01-31 | I18: VALID_TARGET_REFERENCE | J18: HIGH | K18: DIRECT_TARGET_REFERENCE | M18: OABASEV1_c467d5285d646416 | N18: W000030498 | O18: W7208665622
A19: 14 | B19: Ulysses | C19: James Joyce | D19: Joyce among the Cockneys: The East End as Alternative London | E19: The first time James Joyce went to London, both Richard Ellmann and Gordon Bowker's biographies recount, was in May 1900 (jjii 77).1 As well as visiting relatives in East End of city with his father, Joyce sampled all usual delights of cosmopolitan town. As Bowker puts it, John Joyce [showed] his son how to enjoy London - visiting music-halls, theatres, pubs and restaurants.2 It is difficult to ascertain exactly what entertainment young Joyce saw on his trip, but in any case, his being enamoured with halls in particular was clear: upon his return, Joyce would write to his brother Stanislaus proclaiming that the music hall, not poetry, is a criticism of life (jjii 77).With a series of cities already closely associated with author's writing - Dublin and Ulysses-closing Trieste-Zurich-Paris (u 993) - London has hitherto been a somewhat neglected locale in Joyce scholarship. Despite city making repeated appearances in Joyce's works following his 1900 visit, it is only recently that scholars have been encouraged to look towards London, prompted by a broader spatial turn in field. While such studies are welcome, their focus is still relatively narrow in scope. As first metropolis in an empire which included Ireland until 1922, London features most frequently in Joyce criticism as administrative colonial centre. While this interpretation allows significant insight into one facet of capital, it necessarily fails to account for intra-city local differentiation to which Joyce was attuned - homogenising, as it must, London as empire's synecdoche, or at least its symbolic geopolitical centre. The portrait of London in Joyce's novels and poetry, however, is attentive to varying characteristics of city's districts. Indeed, rather than simply rail against empire's heart, it is precisely London's multifaceted nature which Joyce employs to subvert its power as staid colonial centre, using East End of city as a disruptive counterpoint to its supposed propriety and authority.It is, of course, impossible to tell how seriously Joyce intended his line to Stanislaus on music hall to be taken. Yet, whether he meant its elevation above poetry earnestly or ironically, two inferences from Joyce's statement might productively frame his subsequent engagement with East End. The first is concept of hall as an alternative. Juxtaposed against poetry, Joyce proposes music hall as an art form distinguished from more established and, we can reasonably assume, more conventional traditions. The second is music hall as a form able to speak critically of life. Not simply a diversion or play, Joyce here entertains halls as a space in which culture might be assessed and criticised. In what follows, I will suggest that vaudeville East End represented in music hall came to serve this function in Joyce's writing. Contrary to versions of East End which we might expect to find in his works - on which more in a moment - Joyce employs a Cockneyism set against more conservative depictions of city-as-a-whole. A thorough knowledge of area allowed Joyce to selectively contrast tropes and images of East End with their orthodox London counterparts, whether it be in placing ribald Cockney women alongside less locally-inflected British ones, using East End humour to make dignified images of London bathetically ludicrous, or aligning area with other foreign spaces. Tracing use of East End slang, place names, and figures in Dubliners (1914), Ulysses (1922), Finnegans Wake (1939), and Joyce's poetry, this essay will demonstrate how Joyce thus used aesthetic of music hall to fashion a destabilising alternative to London's imperial power.Joyce's general interest in East End is suggested via even most cursory examination of area's fragmented iterations in Finnegans Wake. Numerous appearances of Bow Bells (fw 626. … | F19: 2016.0 | G19: 2016-01-01 | H19: https://doi.org/10.1163/9789004314467_007 | I19: VALID_TARGET_REFERENCE | J19: HIGH | K19: DIRECT_TARGET_REFERENCE | M19: OABASEV1_497d0fea9df9d4ca | N19: W000017666 | O19: W2486871367
A20: 15 | B20: Lamb | C20: Charles Lamb | D20: The portable Charles Lamb | E20: One of the volumes in the distinguished Viking Portable series, this portable carries selections from Lamb's letters, essays, fantasies, poetry and criticism. | F20: 1949.0 | G20: 1949-01-01 | I20: VALID_TARGET_REFERENCE | J20: HIGH | K20: DIRECT_TARGET_REFERENCE | M20: OABASEV1_bc86df8c044a6e1e | N20: W000020329 | O20: W1605818641
A21: 16 | B21: Gray | C21: Thomas Gray | D21: The Magazine of Magazines, September 1756 | E21: Front and back covers and pages from The Magazine of Magazines bound collection. In 1751, Limerick printer Andrew Welsh began printing an edition of the London based The Magazine of Magazines. Welsh, having learnt his trade from his father in Cork, began printing the Magazine, based in a building called ‘The Exchange’ on Nicholas Street, Englishtown, near the cathedral in Limerick. The Limerick publication started life as a direct, almost page for page, reprint of the London edition, printed by William Owen. The publication was a major undertaking for Welsh in Limerick. Welsh claims to have bought an entirely new set of type dedicated to printing the magazine, and the Limerick edition (like many other Irish re-prints of English works) is of better quality than its London counterpart. The Limerick edition was not simply aimed at the immediate urban public; there are three named retailers in Cork as well as one in Dublin. The Magazine, which was published for the best part of two decades, from 1751 to 1769, is a miscellany comprising of extracts from numerous eighteenth century periodicals and journals and covers subjects as diverse as Science, Philosophy, Medicine, Meteorology, Religion, Mythology and Literature to name but a few. It was the first periodical publication to feature Thomas Gray’s famous Elegy Written in a Country Churchyard, in 1751, and published essays and excerpts from towering intellectual figures of the day such as Dr Johnson and Voltaire. Prof Geraldine Sheridan, Dr. Michael Griffin, Yvonne Diggins, Research Assistant. | F21: 2011.0 | G21: 2011-03-08 | I21: VALID_TARGET_REFERENCE | J21: HIGH | K21: DIRECT_TARGET_REFERENCE | L21: Grayの「Elegy」初掲載への言及 | M21: OABASEV1_dfe983daadb4f360 | N21: W000030513 | O21: W7209637656
A22: 17 | B22: Galen | C22: Galen | D22: 6 THE LONG SHADOW OF ANTIQUITY MEDICINE AND PLANTS | E22: The practice of using plants for medical treatment is as old as is mankind.Classical sources (by Dioscorides, Pliny, and Apuleius Platonicus, as well as the theory of humours by Galen) formed the basis for medieval healthcare.The Hippocratic oath (c.fourth century BC) is the earliest expression of medical ethics.Although some medieval recipes are not advisable, others are: people knew the healing potency of hypericum, but were also aware of the poisonous power of hemlock.The quadripartite periodization -monastic medicine / Salernitan medicine / the rise of the universities / scholastic medicine -is based on the relationship of texts to their Greco-Roman sources.Medieval writings like those of Hildegard von Bingen and local vernacular sources were popular in their own time. | F22: 2023.0 | G22: 2023-04-25 | H22: https://doi.org/10.1515/9789048557745-008 | I22: VALID_TARGET_REFERENCE | J22: MEDIUM | K22: VALID_CONTEXTUAL_REFERENCE | L22: 著者名ターゲット：Galenの体液説（著作内容）への言及 | M22: OABASEV1_51dcbfd4a7a824da | N22: W000031472 | O22: W4366994716
A23: 18 | B23: Galen | C23: Galen | D23: Fraeisam Büchlein Petri Hofmanns von d. Praeservation u. Curation d. Fräisams oder Epilepsia an kleinen Kindern, auff Galen. u. Paracels. Art | I23: VALID_TARGET_REFERENCE | J23: MEDIUM | K23: VALID_CONTEXTUAL_REFERENCE | L23: 著者名ターゲット：「auff Galen. u. Paracels. Art」ガレノス流医学への言及 | M23: OABASEV1_d06095b070a8be87 | N23: W000031472 | O23: W7056805148
A24: 19 | B24: Arnold | C24: Matthew Arnold | D24: The Darkening Age: The Christian Destruction of the Classical World. By Catherine Nixey | E24: Pivoting on the vagaries of Late Antiquity, The Darkening Age presents a tendentious, unflinching narrative of how Classical art and literature were systematically obliterated by the Christian movement. Catherine Nixey tracks Christianity’s trail of terror, crisscrossed through time and space. She exposes the presumed smooth denunciation of polytheistic culture as Christian fabrication. This is a book of watershed moments and snapshots of everyday life. It is not a scholastically-encumbered historical narrative but a widely accessible kind of ‘historical travelogue’ (p. xxxv). Nixey builds her account on a wealth of first-hand documents, such as official epistles and polemical diatribes cited discreetly in the book’s back matter. Apposite literary references such as Matthew Arnold’s ‘Dover Beach’ (p. 23) and Umberto Eco’s The Name of the Rose (p.139) enrich the discussion. The structure is circular, beginning and ending with the last Neoplatonist philosopher Damascius of the Athens Academy, which was proscribed by Emperor... | F24: 2020.0 | G24: 2020-07-03 | H24: https://doi.org/10.1093/litthe/fraa014 | I24: VALID_TARGET_REFERENCE | J24: HIGH | K24: DIRECT_TARGET_REFERENCE | L24: Arnoldの「Dover Beach」引用 | M24: OABASEV1_b974cf40325ffbf7 | N24: W000003023 | O24: W3082104555
A25: 20 | B25: Alice in Wonderland | C25: Lewis Carroll | D25: alicia en el pais de las adivinanzas pdf | E25: alicia en el pais de las adivinanzas pdf Rating: 4.4 / 5 (3179 votes) Downloads: 46426 = = = = = CLICK HERE TO DOWNLOAD = = = = = Así pues, el Rey y el verdugo empezaron a corretear de un lado a otro en busca del Gato, mientras el resto del grupo volvía a la partida de croquet alicia-en-el-pais-de-las-adivinanzas-un-cuento-alDownloaded from on by guest bibliotecadigitalilceedumx capítuloen la madriguera del conejo Con hermosas ilustraciones, el Ejército Nacional presenta en la Feria Internacional del Libro de Bogotá, Filbo, un libro, como una la guía pedagógica Missing: pdf · Ciudad de México,abr (EFE) La candidata presidencial del oficialismo mexicano, Claudia Sheinbaum, anticipó este miércoles que durante el segundo debate Missing: pdf Seleccione una colección (fáciles, difíciles, cortas, animales, frutas, niños, etc.) de adivinanzas para descargar e imprimir. Cada PDF tiene tanto las adivinanzas como sus respuestasintroduce al lector en los conceptos básicos del enfoque de los estudios literarios, y analiza la ironía, la parodia, el pastiche, el kitsch, la metaficción, la intertextualidad, el sinsentido y la sátira, entre algunas de las estrategias que quedan al descubierto en la literatura infantil contemporánea La cabeza del Gato empezó a desvanecerse a partir del momento en que el verdugo se fue, y, cuando éste volvió con la Duquesa, había desaparecido totalmente. introduce al lector en los conceptos básicos del enfoque de los estudios literarios, y analiza la ironía, la parodia, el pastiche, el kitsch, la metaficción, la intertextualidad, el sinsentido Alicia en el país de las adivinanzas Raymond Smullyan AtrapalecturasCecilia Beuchat Cecilia Beuchat invita a los niños y niñas a conocer la Resumen y sinopsis de Alicia en el país de las adivinanzas de Raymond Smullyan Raymond Smullyan, lógico, matemático, filósofo, mago y humorista, domina Parodiando el estilo de Lewis Carroll, la Tortuga y el Grifo, el par de gemelos Tweedledee y Tweedledum, los Reyes de Corazones, el pedante huevo Humpty Dumpty y el Caballero Alicia en el país de las adivinanzas Raymond Smullyan Alice in Wonderland Nadia Fabris,Irena Trevisan Lewis Carrolls Alice in Wonderland is retold in this Sinopsis. Raymond Smullyan, lógico, matemático, filósofo, mago y humorista, domina genialmente el arte de plantear con divertidos acertijos arduos problemas de Alicia en el país de las adivinanzas Raymond Smullyan alicia-en-el-pais-de-las-adivinanzas-un-cuento-alDownloaded from on · Comentar. | F25: 2024.0 | G25: 2024-06-10 | H25: https://doi.org/10.5281/zenodo.12270814 | I25: VALID_TARGET_REFERENCE | J25: MEDIUM | K25: VALID_CONTEXTUAL_REFERENCE | L25: スパム的集約テキストだが「Lewis Carrolls Alice in Wonderland」を明示（Smullyanのパロディ紹介文中） | M25: OABASEV1_6528933d9cba7dd6 | N25: W000018284 | O25: W6892801732
A26: 21 | B26: Gray | C26: Thomas Gray | D26: Thomas Gray to Horace Walpole, 4th earl of Orford, Monday, 31 March 1738 [graythOU0010082a1c] | F26: 2014.0 | G26: 2014-07-31 | H26: https://doi.org/10.13051/ee:doc/graythou0010082a1c | I26: VALID_TARGET_REFERENCE | J26: HIGH | K26: DIRECT_TARGET_REFERENCE | L26: 著者名ターゲット：Gray自身の書簡（一次資料） | M26: OABASEV1_d46dfe6be8c6e04c | N26: W000030513 | O26: W4232127913
A27: 22 | B27: Dom Juan | C27: Molière | D27: Dom Juan, Molière, Acte III Scène 4 | F27: 2012.0 | G27: 2012-11-21 | I27: VALID_TARGET_REFERENCE | J27: HIGH | K27: DIRECT_TARGET_REFERENCE | M27: OABASEV1_16de529922e8392f | N27: W000030756 | O27: W18873569
A28: 23 | B28: Louisa May Alcott | C28: Louisa May Alcott | D28: Resumen de tesis. Challenging gender roles in Austen's Pride and Prejudice and Alcott's Little Women and their reception. A comparative study | E28: [ES] Jane Austen es considerada una de las escritoras mas importantes de la historia de la literatura. Desde la publicacion de su primera novela en 1811 hasta las ultimas adaptaciones cinematograficas de sus obras, Austen se ha convertido en un fenomeno mundial. Es casi imposible encontrar a alguien que no haya oido hablar de Jane Austen ya sea por sus novelas o por una de las muchas adaptaciones de sus obras a la pequena o gran pantalla. Por su parte, Louisa May Alcott tambien se convirtio en una escritora muy conocida gracias a su trilogia de Mujercitas; sin embargo, nunca fue tan popular como Jane Austen, especialmente en el mundo academico. A pesar de las aparentes diferencias, es posible establecer paralelismos entre las circunstancias de las autoras, su recepcion y su reciente ascenso a la fama dentro de la cultura popular. Aunque estas novelistas se encuentran separadas por el Oceano Atlantico y mas de medio siglo, como escritoras se enfrentaron a dificultades similares y abordaron experiencias feminocentricas recurrentes, mientras que sus obras fueron elogiadas y criticadas casi por igual. Sin embargo, la investigacion ha demostrado que no existen estudios comparativos exhaustivos que aborden estas similitudes. Para llenar este vacio, la presente tesis ha sido concebida con los siguientes objetivos: primero, exponer como sus trabajos mas conocidos muestran preocupaciones similares con respecto a las mujeres y como a lo largo del tiempo se perciben algunos avances en sus derechos; en segundo lugar, explorar como su sexo y los generos literarios que eligieron han definido su recepcion a lo largo del tiempo, lo que demuestra ciertos prejuicios en criticos y lectores; y, finalmente, analizar las razones de la popularidad actual y como las nuevas adaptaciones simplifican de manera similar sus trabajos. | F28: 2019.0 | G28: 2019-01-01 | I28: VALID_TARGET_REFERENCE | J28: HIGH | K28: DIRECT_TARGET_REFERENCE | L28: Little Women（Mujercitas）を扱う | M28: OABASEV1_6be9aeab4d0f0b65 | N28: W000014515 | O28: W3006176929
A29: 24 | B29: The Ambassadors | C29: Henry James | D29: Representações da descoberta: espaço e epifania em The ambassadors | E29: The aim of this paper is to analyze how the novel The ambassadors, published in 1903 by the American author Henry James (1843-1916), relates the narrative category of space to Lewis Lambert Strether’s epiphany based on some literary concepts conceived by Osman Lins (1976), Iuri Lotman (1978) and James Joyce (1963). We will attempt to show in what manner the revelation of truth is connected to the external space illuminated by the natural light of an inn, conveniently named Cheval Blanc, and harmonizes with the steps of the epiphanic process (integrity, symmetry and radiance), promoting Strether’s self-consciousness. | F29: 2013.0 | G29: 2013-01-01 | I29: VALID_TARGET_REFERENCE | J29: HIGH | K29: DIRECT_TARGET_REFERENCE | M29: OABASEV1_c46b7a49f5544dc5 | N29: W000014023 | O29: W2616175040
A30: 25 | B30: Charles Lamb | C30: Charles Lamb | D30: S imon P. H ull , Charles Lamb, Elia and the London Magazine (London: Pickering & Chatto, 2010), pp. 240. £60 / US $99 hardback. 9781851966615. | F30: 2011.0 | G30: 2011-10-01 | H30: https://doi.org/10.3366/rom.2011.0055 | I30: VALID_TARGET_REFERENCE | J30: HIGH | K30: DIRECT_TARGET_REFERENCE | M30: OABASEV1_f709119bfad1d258 | N30: W000020297 | O30: W2077889046

Sheet Audit 02
A1: OpenAlex R2+A1 Blind Human Audit — R2A1A02
A2: 判定対象：OpenAlex record が target literary work を本当に参照しているか。LLM判定・sampling stratum・risk featureは非表示です。Web検索はしません。
A4: 入力欄 → | I4: Judgment | J4: Confidence | K4: Reason | L4: Reviewer note
A5: Review # | B5: Target title | C5: Target author | D5: OpenAlex record title | E5: OpenAlex abstract | F5: Year | G5: Publication date | H5: DOI | I5: Judgment | J5: Confidence | K5: Reason | L5: Reviewer note | M5: Candidate ID | N5: Project Work ID | O5: OpenAlex Work ID
A6: 26 | B6: Galen | C6: Galen | D6: Prenatal Diagnosis of the Aneurysm of the Vein of Galen by Pulsed Doppler Unit | E6: Aneurysm of the vein of Galen is a rare anomaly. In the severe type, the first clinical manifestation of this anomaly is heart failure after birth. Prenatal diagnosis is important in preventing heart failure during the postnatal period. Here, we report the prenatal diagnosis of a case of aneurysm of the vein of Galen in which we used a pulsed Doppler unit combined with a fetal electrocardiogram-phonocardiogram unit. | F6: 1991.0 | G6: 1991-07-01 | H6: https://doi.org/10.1055/s-2007-999388 | I6: INVALID_TARGET_REFERENCE | J6: HIGH | K6: GENERIC_OR_LEXICAL_TITLE_USE | L6: "vein of Galen"（解剖学上の名祖） | M6: OABASEV1_ffd1703fe30fa950 | N6: W000031472 | O6: W2081917034
A7: 27 | B7: Edgar Allan Poe | C7: Edgar Allan Poe | D7: The Grotesque Elements in Poe’s “Black Cat” and Scudder’s “The White Cat” | E7: The present essay focuses on the grotesque elements in Edgar Allan Poe’s the “Black Cat” and Horace Scudder’s “The White Cat”. Poe’s story is highly embedded with a lot of grotesque elements from the beginning to the end. These elements were presented through strange characters, mysterious happenings, and degradation through death. Poe represents the struggle between the supernatural and the natural which he reinforces through the narrator who struggles to commit wrongdoings. Even in the mist of trying to restrict himself, the narrator still does not know what he did. In “The White Cat,” Scudder employs grotesque elements as well but his application is subtly done unlike Poe whose application is more pronounced. The underlying meaning of this short story is on the spell of enchantment. However, Scudder, like Poe, displays the supernatural events through the characters of the “fairies” who has magical power to change the once a beautiful princess to a white cat. Grotesque includes absurd and bizarre elements and pierces the conventional version of reality. However; in its ability to shock or offend, grotesque helps to expose the vulnerability in human depicted via these absurd element which will be explained in detail in the present study. | F7: 2014.0 | G7: 2014-04-26 | H7: https://doi.org/10.7575/aiac.ijclts.v.2n.2p.42 | I7: VALID_TARGET_REFERENCE | J7: HIGH | K7: DIRECT_TARGET_REFERENCE | M7: OABASEV1_3872a4b2d4dd6dda | N7: W000018534 | O7: W2115502554
A8: 28 | B8: Petronius | C8: Petronius | D8: Petronius és Martialis simplicitas-a | F8: 1947.0 | G8: 1947-01-01 | I8: VALID_TARGET_REFERENCE | J8: HIGH | K8: DIRECT_TARGET_REFERENCE | L8: 著者名ターゲット：Petroniusの文体論 | M8: OABASEV1_e4cc3877ebf1ff31 | N8: W000021772 | O8: W7042323523
A9: 29 | B9: The Hobbit | C9: J.R.R. Tolkien | D9: Paisajes de Tolkien en la Tierra Media. | E9: El artículo reflexiona sobre la carga simbólica y emocional de los dos tipos de escenarios paisajísticos muy marcados y diferenciados que aparecen en la trilogía cinematográfica de “El Hobbit” (The Hobbit) (2012, 2013, 2014), de Peter Jackson.Uno de los paisajes será armónico, tranquilo, edénico y de luz, donde todo funciona en sociedades ideales que habitan criaturas antropomórficos de buena voluntad e intención como son los hobbits y los elfos, mientras que el otro paisaje será oscuro y desolador habitado por seres terroríficos como trasgos y orcos, dominados por una fuerza misteriosa de siniestro poder llamada el Nigromante que siembra el mal en su sombrío territorio. A través del universo creado por el escritor y profesor J.R.R.Tolkien y de su imaginaria y fascinante Tierra Media, se analiza el escenario paisajístico cinematográfico intentando buscar las claves que lo definan a medida que es recorrido por la comunidad formada por el mago Gandalf el Gris, (Ian McKellen),el hobbit Bilbo Bolsón, (Martin Freeman), el rey enano Thorin Escudo de roble (Richard Armitage) y los otros doce enanos que le acompañan, partiendo del paisaje edénico de la Comarca y del armonioso y casi perfecto Rivendel, pasando por las tierras siniestras y de penumbra donde el paisaje aparece muy en consonancia con la obra de pintores y grabadores del romanticismo como Piranesi o Caspar David Friedrich, cuyas obras se reflejan a la perfección en el Bosque de Trolls, Dol Guldur en el Bosque Negro, y la Ciudad de los Trasgos en busca del antiguo reino de los enanos en Erebor. | F9: 2018.0 | G9: 2018-12-10 | H9: https://doi.org/10.83190/yn8d9660 | I9: VALID_TARGET_REFERENCE | J9: MEDIUM | K9: VALID_CONTEXTUAL_REFERENCE | L9: Peter Jacksonの映画三部作が主対象だが、原作「The Hobbit」とTolkienを明示。映画化作品経由の参照 | M9: OABASEV1_060ac2b6934cc9ab | N9: W000013953 | O9: W7172534944
A10: 30 | B10: D.H. Lawrence | C10: D. H. Lawrence | D10: Westernness: A Meditation by Alan Williamson | E10: B o o k R e v i e w s Westernness: A Meditation. By Alan Williamson. Charlottesville: University of Virginia Press, 2006. 182 pages, $29.50. Reviewed by Diane Quantic Wichita State University Alan Williamson calls his study Westemness “a meditation,” “a fugue of accu­ mulating impressions” (7). Although the title seems sweeping, Williamson focuses primarily on afew authors and works from California and New Mexico. For example, in his first chapter, “Cather and Romance,” he considers only Death Comes for the Archbishop (1927), with brief mention of Song of the Lark (1915) and O Pioneers! (1913). In subsequent chapters, he treats “Yosemite Painters” Albert Bierstadt, Thomas Hill, and William Keith in just three-anda -half pages but with fine color reproductions of their works. D. H. Lawrence Photographer unknown. “Theodore Roosevelt and his dog Skip, on a bearhunt , West Divide Creek, near New Castle, Colorado, April 1905.” Neg. no. 335695. Courtesy of the American Museum ofNatural History Library. b o o k R e v ie w s and Yvor Winters are “Two Convalescents.” In four pages, he mentions Georgia O ’Keeffe in the context of Las Trampas and Chimayo. There are discussions of the Tonalism of the early-twentieth-century Monterrey painters and Robinson Jeffers. Steinbeck is considered in the context of the Tao. Raymond Chandler and the poets (unknown to this reader) James McMichael and Frank Bidart are covered in a chapter on Southern California. He places his discussion of Leslie Marmon Silko’sCeremony (1977) in a chapter titled “Highway 66” that focuses on negative aspects of European American culture. The California painter Wayne Thiebaud gets only four-and-a-half pages, but the poet Gary Snyder is central to two chapters, including one on the influence of Eastern culture on California poets. Finally, Williamson considers Montana and Young Men and Fire (1992) by Norman Maclean. To say the least, I find this an odd mix of “westemness” that means some­ thing quite different to me and, I would guess, to most students of western literature than it does to Williamson. The term “meditation,” like the recently controversial “memoir,” apparently gives an author more authority over his material than does a “systematic history,” for which Williams admits he “lackjs] the competence” (7). I would agree: it seems odd to read commentary on Cather’sromanticism and Death Comes for the Archbishop in the context of Richard Chase’sThe American Novel and Its Tradition (1957), citing the Vintage edition of the novel, with no reference to Susan Rosowski’sstudy of The Voyage Perilous (1986) or the scholarly edition of the text. Williamson’snotes vary in length and number from chapter to chapter, but in all of his discussions he relies on only a few sources outside his primary texts. He does not bring to his “meditation” the depth and range of scholarship one usually expects from a scholarly text. Nevertheless, I find his readings of the works by Cather, Steinbeck, and Maclean to be refreshing and insightful. Perhaps the key to appreciating a “meditation” is to recognize it as the author’s attempt to share a thoughtful consideration of certain texts in an effort to place those works within one’s own sense of “westemness.” Even though Williamson does not succeed in explaining his concept of the term adequately, he does add to my appreciation of several texts that embody my own sense of “westemness.” ... | F10: 2007.0 | G10: 2007-01-01 | H10: https://doi.org/10.1353/wal.2007.0027 | I10: VALID_TARGET_REFERENCE | J10: HIGH | K10: DIRECT_TARGET_REFERENCE | L10: 著者名ターゲット：評対象書にD. H. Lawrenceを扱う章あり | M10: OABASEV1_0b80a14c51a41611 | N10: W000030498 | O10: W2761953010
A11: 31 | B11: Ulysses | C11: James Joyce | D11: Homer, Turko, Little Harry: Cultural Memory and the Ethics of Premediation in James Joyce’s Ulysses | F11: 2019.0 | G11: 2019-06-06 | I11: VALID_TARGET_REFERENCE | J11: HIGH | K11: DIRECT_TARGET_REFERENCE | M11: OABASEV1_c1b54bf68ca97b4e | N11: W000030950 | O11: W7056874470
A12: 32 | B12: A Rose for Emily | C12: William Faulkner | D12: Teaching Hemingway and Modernism ed. by Joseph Fruscione | E12: Reviewed by: Teaching Hemingway and Modernism ed. by Joseph Fruscione Michael Von Cannon Teaching Hemingway and Modernism. Ed. Joseph Fruscione. Kent, OH: Kent State UP, 2015. 240 pp. Paper $40.00. As part of the "Teaching Hemingway" series, Joseph Fruscione's essay collection Teaching Hemingway and Modernism follows Lisa Tyler's Teaching Hemingway's A Farewell to Arms and Peter L. Hays's Teaching Hemingway's The Sun Also Rises (2008) and precedes Alex Vernon's Teaching Hemingway and War (2016), Verna Kale's Teaching Hemingway and Gender (2016) and Kevin Maier's soon-to-be-published Teaching Hemingway and the Natural World (2017). In the forward to Fruscione's volume, Mark P. Ott notes the rationale for shifting away from specific novels and toward broader concepts: "To promote their usefulness to instructors and professors—from high schools, community colleges, and universities—the newest volumes in this series are organized thematically rather than around a single text." In the introduction and the fifteen pedagogically oriented essays that follow, the volume explores Hemingway and the "theme" of modernism through three sections on significant people, places, and cultural and theoretical contexts. Written by teacher-scholars—ranging from tenured faculty to adjuncts, from university administrators to cofounders of nonprofit organizations—these essays discuss the relationship between Hemingway and Gertrude Stein, Wallace Stevens, William Faulkner, and Zora Neale Hurston; the writer's rootedness to places such as Paris and Spain; and contexts including avant-garde art, warfare, postmodernism, and the digital age. Most importantly, contributors not only exhibit cutting-edge research but also stress innovative teaching practices both within and outside the traditional classroom setting. In the first section, contributors show how Hemingway's ostensible simplicity can help students decipher works by notoriously difficult modernist writers while, at the same time, deepening our appreciation of Hemingway's own complexity. Julie Goodspeed-Chadwick and Katie Owens-Murphy each compare Stein's portraits and narratives (e.g. "Picasso," Three Lives, and The Making of Americans) to In Our Time and Death in the Afternoon, contending that the juxtaposition provides access to stylistic similarities, specifically the writers' uses of repetition and elision. Likewise, Phillip Beard argues that "Big Two-Hearted River" and To Have and Have Not can help students understand Stevens's poetics of "extraordinary actuality" and, in turn, Hemingway's ecological understanding. James B. Carothers brings readers into his Hemingway and Faulkner undergraduate classroom, delving into the assigned reading list, class discussions (such as those on similarities between "The Short Happy [End Page 135] Life of Francis Macomber" and "A Rose for Emily"), essay prompts, and exam questions. For instance, Carothers warns against assignments or essay questions on the problematic Hemingway code; however, he does usefully suggest, "What you can do is ask students to consider the differences between the hero, the protagonist, and the central character, since the modern world that Hemingway and Faulkner confronted did not offer the heroic opportunity" (44). Most striking, Anna Lillios outlines her American Literature II unit on Hemingway and Hurston, in which she provides a day-by-day plan for The Sun Also Rises and Their Eyes Were Watching God. Like Carothers, she also offers suggestions for class discussions and essays that explore the gender and race dimensions of these modernist pilgrimage novels. Not surprisingly, the majority of essays in the second section (on place) center on Hemingway's Paris. Beginning with an immersive tour of her study-abroad course on American expatriate writers, Meg Gillette insightfully demonstrates how visits to museums (such as the Museum of Jewish Art and History, the Anthropology Museum, and the Musée d'Orsay) and other city sites—including statues, monuments, and memorials—help students examine the race, ethnicity, and gender in The Sun Also Rises, a novel that starts to read like a kind of postwar travelogue. She also helpfully offers tips for constructing a course with similar learning objectives but without the study-abroad requirement. Adam R. McKee focuses on the influence of Stein, James Joyce, and Paul Cézanne on the young writer's Paris-based experimentation, whereas David Barnes traces Ezra Pound's influence in order to recapture the political and socioeconomic aspects of In Our Time and... | F12: 2017.0 | G12: 2017-01-01 | H12: https://doi.org/10.1353/hem.2017.0009 | I12: VALID_TARGET_REFERENCE | J12: HIGH | K12: DIRECT_TARGET_REFERENCE | L12: 抄録後半で "A Rose for Emily" を明示的に言及 | M12: OABASEV1_9a0633e87f01b3c8 | N12: W000030723 | O12: W2615321001
A13: 33 | B13: Lamb | C13: Charles Lamb | D13: A General Introduction to Charles Lamb. Together with a Special Study of His Relation to Robert Burton, the Author of the Anatomy of Melancholy ... | F13: 2009.0 | G13: 2009-08-10 | I13: VALID_TARGET_REFERENCE | J13: HIGH | K13: DIRECT_TARGET_REFERENCE | M13: OABASEV1_94fe686e375d12c2 | N13: W000020329 | O13: W423100859
A14: 34 | B14: Henry James | C14: Henry James | D14: Women’s Cultural Identity and Desire in the Works of Henry James, Edith Wharton and Gwang-su Yi | F14: 2018.0 | G14: 2018-05-31 | H14: https://doi.org/10.21084/jmball.2018.05.36.2.43 | I14: VALID_TARGET_REFERENCE | J14: HIGH | K14: DIRECT_TARGET_REFERENCE | M14: OABASEV1_b51aaa2150e484bc | N14: W000014024 | O14: W2808989167
A15: 35 | B15: Novels | C15: Jules Verne | D15: Jules Verne, Nina y un nuevo Mediterráneo | E15: EnglishIn the novel Hector Servadac by Jules Verne, on January 1st, a man challenges another man to a duel on the Algerian coast because both of them are in love with the same woman, a young widow. That night a meteorite crashes into the Earth taking away the western Mediterranean coast. Together with its inhabitants, this area keeps spinning around the Solar System, on its own orbit, for two years before returning to its original place. This plot allows the French author to evoke the regeneration of the society of his time and, despite the widely spread idea that women have little importance in his novels, we meet Nina, an essential character for such a regeneration to take place. francaisJules Verne dans son roman Hector Servadac raconte que, le premier janvier, deux hommes vont se defier en duel sur la cote d’Algerie pour une rivalite amoureuse, celle d’une jeune veuve. Juste la nuit d’avant, une comete heurte la Terre arrachant un morceau, la cote occidentale de la Mediterranee. Ce nouvel astre avec ses habitants devient une partie du systeme solaire et tourne, avec sa propre orbite, pendant deux ans avant de retourner a son lieu d’origine. Avec cette aventure cosmographique, l’auteur francais cherche a montrer un modele de regeneration a la societe de son epoque. Malgre l’idee si repandue a propos d’une presence minimale de la femme dans ses romans, nous decouvrirons que Nina est un personnage essentiel pour que cette renaissance soit possible. | F15: 2019.0 | G15: 2019-01-01 | I15: VALID_TARGET_REFERENCE | J15: MEDIUM | K15: VALID_CONTEXTUAL_REFERENCE | L15: ターゲット題名「Novels」は総称的。Verneの小説Hector Servadacを論じる | M15: OABASEV1_f1937b330392851f | N15: W000000749 | O15: W3207142652
A16: 36 | B16: The Island of Dr. Moreau | C16: H. G. Wells | D16: Burning Out the Animal: The Failure of Enlightenment Purification in H. G. Wells’s The Island of Dr. Moreau | E16: J acques Derrida’s recent and recurring interest in the problem of the animal signals the critical recognition in cultural theory of a non- human “other” that is crucial to our modernity and to our Western philosophical heritage. Derrida traces a certain recalcitrant humanism in Western metaphysical thought—especially in the work of such cardinal thinkers as Aristotle, Freud, Heidegger, and Levinas—which “continues to link subjectivity with man” 1 and withhold it from the animal. In broad theoretical terms, Derrida characterizes the sacrificial structure of Western subjectivity as one that maintains the status of the “human” by a violent abjection, destruction, and disavowal of the “animal.” In other words, the sanctity of humanity depends upon our difference from animals, our repression of animality, and the material reinstantiation of that exclusion through various practices such as meat-eating, hunting, and medical experimentation. These keywords were added by machine and not by the authors. This process is experimental and the keywords may be updated as the learning algorithm improves. | F16: 2005.0 | G16: 2005-01-01 | H16: https://doi.org/10.1007/978-1-137-09411-7_8 | I16: VALID_TARGET_REFERENCE | J16: HIGH | K16: DIRECT_TARGET_REFERENCE | M16: OABASEV1_508cddaa35461983 | N16: W000017418 | O16: W2529094040
A17: 37 | B17: Petronius | C17: Petronius | D17: Petronius’ Talking Birds: Mimicry and Death in theCena Trimalchionis | F17: 2019.0 | G17: 2019-12-26 | H17: https://doi.org/10.1086/706448 | I17: VALID_TARGET_REFERENCE | J17: HIGH | K17: DIRECT_TARGET_REFERENCE | M17: OABASEV1_82e992bab839c69b | N17: W000021772 | O17: W2997367910
A18: 38 | B18: Death on the Nile | C18: Agatha Christie | D18: [Watch-HD]] Movie Death on the Nile (2020) Full Online Full qzo | E18: CLICK THIS LINK TO WATCH >> https://iyxwfilm.xyz/movie/505026/death-on-the-nile.html\n\n\n\nMovieS.4K.UltraHD!~FERVOR* HOW to Watch Death on the Nile Online legally & For Free; here you can Watch Full Movie 3D Action HD Watch Death on the Nile (2020) Online Free Full Movie, 8 Movies to Watch ‘Death on the Nile’ Film, Full. Death on the Nile 2020 Full Movie Free Streaming Online with English Subtitles ready for download,Death on the Nile 2020 720p, 1080p, BrRip, DvdRip, High Quality.\n\n\n\n█████████████████████████████████████████████████\n\n\n\nWatch NOW: https://iyxwfilm.xyz/movie/505026/death-on-the-nile.html\n\nNow : https://iyxwfilm.xyz/movie/505026/death-on-the-nile.html\n\nDeath on the Nile\n\n\n\nGenre: Crime, Mystery, Drama, Thriller\n\n\n\nStars: 20th Century Studios, Scott Free Productions, Kinberg Genre, The Mark Gordon Company, TSG Entertainment, The Estate of Agatha Christie & United States of America\n\n\n\nRelease date: 2020-12-17 (0min)\n\nCrime, Mystery, Drama, Thriller20th Century Studios, Scott Free Productions, Kinberg Genre, The Mark Gordon Company, TSG Entertainment, The Estate of Agatha Christie & United States of America\n\n\n\nSYNOPSIS AND DETAILS :\n\nBelgian sleuth Hercule Poirot’s Egyptian vacation aboard a glamorous river steamer turns into a terrifying search for a murderer when a picture-perfect couple’s idyllic honeymoon is tragically cut short.\n\nBEST!~EXPRES*Movies.4K-How to watch Death on the Nile FULL Movie Online Free? HQ Reddit [DVD-ENGLISH] Death on the Nile (2020) Full Movie Watch online free Dailymotion [#Death on the Nile] Google Drive/[DvdRip-USA/Eng-Subs] Death on the Nile! (2020) Full Movie Watch online No Sign Up 123 Movies Online !! Death on the Nile (2020) [EMPIREZ] | Watch Death on the Nile Online 2020 Full Movie Free HD.720Px|Watch Death on the Nile Online 2020 Full MovieS Free HD !! Death on the Nile (2020) with English Subtitles ready for download, Death on the Nile 2020 720p, 1080p, BrRip, DvdRip, Youtube, Reddit, Multilanguage and High Quality. Full Movie download at Openload, Netflix, Filmywap, movierulz, StreamLikers, Tamilrockers, putlockers, Streamango, 123movies.\n\n\n\nIn Death on the Nile, the gang is back but the game has changed. As they return to rescue one of their own, the players will have to brave parts unknown from arid deserts to snowy mountains, to escape the world’s most dangerous game. Death on the Nile (2020) [CARTERET] | Watch Death on the Nile Online 2020 Full Movie Free HD.720Px|Watch Death on the Nile Online 2020 Full MovieS Free HD !! Death on the Nile (2020) with English Subtitles ready for download, Death on the Nile 2020 720p, 1080p, BrRip, DvdRip, Youtube, Reddit, Multilanguage and High Quality.\n\n\n\nWatch Death on the Nile Online Free Streaming, Watch Death on the Nile Online Full Streaming In HD Quality, Let’s go to watch the latest movies of your favorite movies, Death on the Nile. come on join us!!\n\n\n\nWhat happened in this movie?\n\n\n\nI have a summary for you. It’s the first rose ceremony of the movie and the drama is already ratcheted up! Two very different men – Blake and Dylan – have their hearts set on handing their rose to HDeath on the Nileh G., but who will offer it to her and will she accept?\n\n\n\nAll About The movies\n\n\n\nEuphoria centers on CDC researcher Abby Arcane. When she returns to her childhood home of Houma, Louisiana, in order to investigate a deadly swamp-borne virus, she develops a surprising bond with scientist Alec Holland — only to have him tragically taken from her. But as powerful forces descend on Houma, intent on exploiting the swamp’s mysterious properties for their own purposes, Abby will discover that the swamp holds mystical secrets, both horrifying and wondrous — and the potential love of her life may not be after all.\n\n\n\nPublic Group\n\n\n\n2 minutes ago\n\n\n\nmoviesfree co Watch Online Death on the Nile: Complete movies Free Online Full Strengthens Crusaders and mountan Moorish comders rebelled against the British crown.\n\n\n\nHow long have you fallen asleep during Death on the Nile Movie? The music, the story, and the message are phenomenal in Death on the Nile. I have never been able to see another Movie five times like I did this. Come back and look for the second time and pay attention.\n\n\n\nWatch Death on the Nile WEB-DL movies This is losing less lame files from streaming Death on the Nile, like Netflix, Amazon Video.\n\n\n\nHulu, Death on the Nilechy roll, DiscoveryGO, BBC iPlayer, etc. These are also movies or TV shows that are downloaded through online distribution sites, such as iTunes.\n\n\n\nThe quality is quite good because it is not re-encoded. Video streams (H.264 or H.265) and audio (AC3 / Death on the Nile) are usually extracted from iTunes or Amazon Video and then reinstalled into the MKV container without sacrificing quality. Download Euphoria Movie Season 1 Movie 6 One of the streaming movies.\n\n\n\nWatch Death on the Nile Miles Morales conjures his life between being a middle school student and becoming Death on the Nile.\n\n\n\nHowever, when Wilson “Kingpin” Fiskuses as a super collider, another Captive State from another dimension, Peter Parker, accidentally ended up in the Miles dimension.\n\n\n\nWhen Peter trained the Miles to get better, Spider-, they soon joined four other Death on the Nile from across the “Spider-Verse”. Because all these conflicting dimensions begin to destroy Brooklyn, Miles must help others stop Fisk and return everyone to their own dimensions.\n\n\n\nthe industry’s biggest impact is on the DVD industry, which effectively met its destruction by mass popularizing online content. The emergence of streaming media has caused the fall of y DVD rental companies such as Blockbuster. In July 2020, an article from the New York Times published an article about Netflix DVD, No ches Frida 2s. It was stated that Netflix was continuing their DVD No. No Frida 2s with 5.3 million customers, which was a significant decrease from the previous year. On the other hand, their streaming, No ches Frida 2s, has 65 million members. In a March 2020 study that assessed “The Impact of movies of Streaming on Traditional DVD Movie Rentals” it was found that respondents did not buy DVD movies nearly as much, if ever, because streaming had taken over the market.\n\n\n\nSo we get more space adventures, more original story material and more about what will make this 21st MCU movie different from the previous 20 MCU films.\n\n\n\nWatch Final Space Season 2 — Movie 6, viewers don’t consider the quality of movies to differ significantly between DVDs and online streaming. Problems that according to respondents need to be improved by streaming movies including fast forwarding or rewinding functions, and search functions. This article highlights that streaming quality movies as an industry will only increase in time, because advertising revenues continue to soar on an annual basis across industries, providing incentives for the production of quality content.\n\n\n\nHe is someone we don’t see happening. Still, Brie Larson’s resume is impressive. The actress has been playing on TV and film sets since she was 11 years old. One of those confused with Swedish player Alicia Vikander (Tomb Raider) won an Oscar in 2016. She was the first Marvel movie star with a female leader. . And soon, he will play a CIA agent in a movies commissioned by Apple for his future platform. The movies he produced together.\n\n\n\nUnknown to the general public in 2016, this “neighbor girl” won an Academy Award for best actress for her poignant appearance in the “Room”, the true story of a wo who was exiled with her child by predators. He had overtaken Cate Blanchett and Jennifer Lawrence, both of them had Death on the Nile out of statues, but also Charlotte Rampling and Saoirse Ronan.\n\n\n\nWatch Death on the Nile Movie Online Blu-rayor Bluray rips directly from Blu-ray discs to 1080p or 720p (depending on source), and uses the x264 codec. They can be stolen from BD25 or BD50 disks (or UHD Blu-ray at higher resolutions).\n\n\n\nBDRips comes from Blu-ray discs and are encoded to lower resolution sources (ie 1080p to720p / 576p / 480p). BRRip is a video that has been encoded at HD resolution (usually 1080p) which is then transcribed to SD resolution. Watch Death on the Nile The BD / BRRip Movie in DVDRip resolution looks better, however, because the encoding is from a higher quality source.\n\n\n\nBRRips only from HD resolution to SD resolution while BDRips can switch from 2160p to 1080p, etc., as long as they drop in the source disc resolution. Watch Death on the Nile Movie Full BDRip is not transcode and can move down for encryption, but BRRip can only go down to SD resolution because they are transcribed.\n\n\n\nAt the age of 26, on the night of this Oscar, where he appeared in a steamy blue gauze dress, the reddish-haired actress gained access to Hollywood’s hottest actress club.\n\n\n\nBD / BRRips in DVDRip resolution can vary between XviD orx264codecs (generally measuring 700MB and 1.5GB and the size of DVD5 or DVD9: 4.5GB or 8.4GB) which is larger, the size fluctuates depending on the length and quality of release, but increasingly the higher the size, the more likely they are to use the x264 codec.\n\n\n\nWith its classic and secret beauty, this Californian from Sacramento has won the Summit. He was seen on “21 Jump Street” with Channing Tatum, and “Crazy Amy” by Judd Apatow. And against more prominent actresses like Jennifer Lawrence, Gal Gadot or Scarlett Johansson, Brie Larson signed a seven-contract deal with Marvel.\n\n\n\nThere is nothing like that with Watch The Curse of La Llorona Free Online, which is signed mainly by women. And it feels. When he’s not in a combination of full-featured superheroes, Carol Danvers Death on the Niles Nirvana as Death on the Niley anti-erotic as possible and proves to be very independent. This is even the key to his strength | F18: 2020.0 | G18: 2020-10-17 | H18: https://doi.org/10.5281/zenodo.4098802 | I18: VALID_TARGET_REFERENCE | J18: MEDIUM | K18: VALID_CONTEXTUAL_REFERENCE | L18: 違法配信スパム。2020年映画版（Christie原作、Estate明記）への参照。映画化作品経由 | M18: OABASEV1_1b43ff02a9b1b3b0 | N18: W000020875 | O18: W6931456987
A19: 39 | B19: Works | C19: Wilkie Collins | D19: Review: Wilkie Collins, Medicine and the Gothic, by Laurence Talairach-Vielmas | E19: Book Review| June 01 2011 Review: Wilkie Collins, Medicine and the Gothic, by Laurence Talairach-Vielmas Laurence Talairach-VielmasWilkie Collins, Medicine and the Gothic. Cardiff: University of Wales Press, 2009. Pp. x + 248. $85. Jessica Straley Jessica Straley University of Utah Search for other works by this author on: This Site PubMed Google Scholar Nineteenth-Century Literature (2011) 66 (1): 116–119. https://doi.org/10.1525/ncl.2011.66.1.116 Views Icon Views Article contents Figures & tables Video Audio Supplementary Data Peer Review Share Icon Share Facebook Twitter LinkedIn MailTo Tools Icon Tools Get Permissions Cite Icon Cite Search Site Citation Jessica Straley; Review: Wilkie Collins, Medicine and the Gothic, by Laurence Talairach-Vielmas. Nineteenth-Century Literature 1 June 2011; 66 (1): 116–119. doi: https://doi.org/10.1525/ncl.2011.66.1.116 Download citation file: Ris (Zotero) Reference Manager EasyBib Bookends Mendeley Papers EndNote RefWorks BibTex toolbar search Search Dropdown Menu toolbar search search input Search input auto suggest filter your search All ContentNineteenth-Century Literature Search This content is only available via PDF. © 2011 by The Regents of the University of California Article PDF first page preview Close Modal You do not currently have access to this content. | F19: 2011.0 | G19: 2011-06-01 | H19: https://doi.org/10.1525/ncl.2011.66.1.116 | I19: VALID_TARGET_REFERENCE | J19: MEDIUM | K19: VALID_CONTEXTUAL_REFERENCE | L19: ターゲット題名「Works」は総称的。Collins作品研究の書評 | M19: OABASEV1_364df22a5aab93f3 | N19: W000005717 | O19: W2325081710
A20: 40 | B20: Ficciones | C20: Jorge Luis Borges | D20: O AUTOR E A PERSONAGEM: A CONTRIBUIÇÃO DE CONCEITOS BAKHTINIANOS NA LEITURA DE UM CONTO DE BORGES | E20: Considering theoretical concepts presented by Mikhail Bakhtin in Problems of Dostoevsky's Poetics and Aesthetics of verbal creation, this essay intends to discuss the categories of autor and character in fiction, understanding them in their mutual discursive relations.Although, in Bakhtin's works, the discussion in correlated mostly to the novel as a genre (with an special emphasis on Dostoevsky's novels), this essay reconsiders the discussion from the viewpoint of Macabéa -Revista Eletrônica do Netlli | V. 4, N. 2, p. 13-20, jul.-dez.2015 another literary genre, the short story.To do so, we analyze the narrative relations found in "The form of the sword", a short story written by Jorge Luis Borges and published in his book Ficciones. ResumoPartindo das concepções teóricas apresentadas por Mikhail Bakhtin em Problemas da poética de Dostoiévski e em Estética da criação verbal, o presente artigo pretende discutir as categorias ficcionais de autor e personagem, compreendendo-as em suas mútuas relações discursivas. | F20: 2016.0 | G20: 2016-05-25 | H20: https://doi.org/10.47295/mren.v4i2.1086 | I20: VALID_TARGET_REFERENCE | J20: HIGH | K20: DIRECT_TARGET_REFERENCE | M20: OABASEV1_d932721f4bb124e6 | N20: W000000893 | O20: W2590018682
A21: 41 | B21: Dracula | C21: Bram Stoker | D21: Specularity and engulfment: Francis Ford Coppola and Bram Stoker's Dracula | E21: In this chapter, I shall discuss a group of recent American films that presents a distinct variation of the horror film I call &s;yuppie horror&s;. This group includes, among others, After Hours (1985), Desperately Seeking Susan (1985), Something Wild (1986), Fatal Attraction (1987), Bad Influence (1991), Pacific Heights (1990), The Hand that Rocks the Cradle (1992), Poison Ivy (1992), Single White Female (1992) and The Temp (1993). Some of these films, to be sure, reveal affinities to other genres: both Something Wild and Desperately Seeking Susan, for example, possess elements of screwball comedy — a genre, it is worth noting, that shares with horror the irruption of the irrational into the workaday world. Yet, to a significant extent, all these films retain much of the style and syntax of the horror genre, while substituting a new set of semantic elements. And although it may be argued that some of these movies exhibit only a minimal relation to the horror film, together they form a distinct generic cycle that, instead of expressing the repression and contradictions of bourgeois society generally, as many critics agree is central to the ideology of the genre, 1 specifically addresses the anxieties of an affluent culture in an era of prolonged recession. | F21: 2013.0 | G21: 2013-04-15 | H21: https://doi.org/10.4324/9780203349847-22 | I21: VALID_TARGET_REFERENCE | J21: MEDIUM | K21: DIRECT_TARGET_REFERENCE | L21: 題名は "Bram Stoker's Dracula"（映画）を明示。抄録は別論文（yuppie horror）の誤付与と思われる | M21: OABASEV1_914322e90312cd53 | N21: W000031539 | O21: W2143212400
A22: 42 | B22: The Heritage of the Desert | C22: Zane Grey | D22: Translating Southwestern Landscapes: The Making of an Anglo Literary Region by Audrey Goodman | E22: 3 0 4 WAL 3 8 . 3 F a l l 2 0 0 3 “an absent signifier” (56). While agreeing with Donald Worster that Stein­ beck looks favorably on the myth of the yeoman, he argues that this nostalgia “does not detract from the book’s success in subverting the hydroindustrial paradigm” (57). Cassuto continues his look at the power inherent in the excesses of fed­ eral hydrologic projects by examining Abbey’s The Monkey Wrench Gang through “faux potlatch," based on Georges Bataille’s theories. For Cassuto the monkey wrenchers’ plan to blow up Glen Canyon Dam represents “the ultimate potlatch” and a replacement of the faux potlatch of federal control (81). In examining Barbara Kingsolver’s Animal Dreams, Cassuto turns to sys­ tems theory to discuss “the difficulties inherent in the construction of a postReclamation era” (97). His analysis underscores the importance of differing definitions used by the characters on both sides of the dam dispute. As with Austin’s novel, Cassuto reads the novel’s positive ending as forced, suggesting the success of Kingsolver’s characters is a limited victory, one that offers little hope in terms of changing water policy. Throughout the book Cassuto, who now practices environmental law, gives a clear overview of a century of water politics, contributing to western American literature by showing the ways in which dominant cultural myths not only influence novelists, but also creators of water policy. Translating Southwestern Landscapes: The Making of an Anglo Literary Region. By Audrey Goodman. Tucson: U n iversity o f A rizona Press, 2002. 224 pages, $40.00. Reviewed by Maureen Salzer U niversity of W isconsin, Superior In this interdisciplinary study of the cultural forces that have constructed the American Southwest as a distinct region, Audrey Goodman draws upon cultural geography, borderland studies, postmodern ethnography, ethnocriticism , economic analysis, and theories of tourism to construct an analysis of the Southwest as a series of imagined translations. Goodman focuses on East Coast bourgeois writers and photographers who represented the Southwest to Englishspeaking , dominant-culture readers: Charles Lummis, Zane Grey, Mark Strand, Ansel Adams, Mary Austin, and Willa Cather. Goodman argues that defini­ tions of region are necessarily partial and contingent, that constructions of region are culturally and aesthetically specific, and that closure usefully eludes us in an imagined southwestern landscape. The book begins with popular writers Charles Lummis and Zane Grey. Goodman finds value in Lummis’s use of multiple written genres and his doc­ umentary photography, briefly discussing his 1892 A Tramp across the Continent and comparing his translations of Pueblo stories (1894’s The Man Who Married the Moon and Other Pueblo Indian Folk-Stories) to those of Frank Hamilton B o o k r e v i e w s 3 0 5 Cushing. Goodman rightly emphasizes the difficulties of intercultural transla­ tion. Next Goodman considers how Zane Grey’s early novels—The Heritage of the Desert (1910), The Riders of the Purple Sage (1912), Desert Gold (1913), and The Rainbow Trail (1915)— establish utopian visions of the Southwest within a network of social, political, and economic forces, including religion, eco­ nomic opportunity, gender roles, borderlands issues, and personal property rights. A sublime or enchanted landscape, free of history, coexists with cultural difference and lack of economic parity. Next, art photographers Mark Strand and Ansel Adams, both protégés of Alfred Stieglitz, are shown to have developed their work in relation to earlier documentary photographers Carleton Watkins and William Henry Jackson, who primarily produced landscapes, and to Ben Wittick, Lummis, and Edward Curtis, whose subjects included Native people and their communities. Their work is contrasted with the innovative work of contemporary photographer Alex Harris. Goodman’s chapter on Mary Austin and the modernist Southwest dis­ cusses the then current popularity of things Native, Mabel Dodge Luhan and her problematic participation in Native cultures, D. H. Lawrence’s visions of the American Southwest, and Boasian anthropology. Austin’s early regionalist work in Land of Little Rain (1903) is found to have clearly modernist narra­ tive structures that differentiate it from earlier local color writings. Austin’s later subjective and intuitive translations of Native verbal art are rightly seen as partial and... | F22: 2003.0 | G22: 2003-01-01 | H22: https://doi.org/10.1353/wal.2003.0003 | I22: VALID_TARGET_REFERENCE | J22: HIGH | K22: DIRECT_TARGET_REFERENCE | L22: 抄録後半で The Heritage of the Desert (1910) を明示 | M22: OABASEV1_5a8d0e1f0cef9c69 | N22: W000021197 | O22: W2764107105
A23: 43 | B23: The Black Cat | C23: Edgar Allan Poe | D23: Analysis of Figurative Language in The Tell Tale Heart and Other Stories by Edgar Allan Poe | E23: This study presents a detailed analysis of figurative language in Edgar Allan Poe's short stories, specifically The Tell-Tale Heart, The Black Cat, and The Fall of the House of Usher. Using a qualitative, descriptive methodology, the research investigates various forms of figurative language, such as metaphor, simile, personification, and hyperbole, to examine their role in developing the themes of psychological horror and the macabre. The findings reveal that Poe employs figurative language strategically to enhance the unsettling atmosphere of his narratives. Alliteration is used extensively to create rhythmic and phonetic cohesion, heightening the eerie and suspenseful mood characteristic of his works. In contrast, allusion is used sparingly, suggesting Poe’s selective approach to external references. Metaphors and personification are pivotal in illustrating psychological states such as guilt, paranoia, and existential dread, contributing significantly to the depth and resonance of his themes. These stylistic choices demonstrate how Poe's innovative use of language immerses readers in the complexities of the human psyche, offering a profound exploration of mortality and moral conflict. By intertwining linguistic artistry with psychological depth, Poe’s narratives invite readers to confront the darker facets of existence. This study underscores Poe’s enduring influence on literary expression, showcasing how his mastery of figurative language has shaped the genre of psychological horror and cemented his legacy as a pioneer in exploring the macabre through nuanced and evocative storytelling. | F23: 2024.0 | G23: 2024-08-30 | H23: https://doi.org/10.32877/narasi.v1i3.1973 | I23: VALID_TARGET_REFERENCE | J23: HIGH | K23: DIRECT_TARGET_REFERENCE | M23: OABASEV1_c618dcf76ce56b0a | N23: W000018553 | O23: W4406009583
A24: 44 | B24: Gray | C24: Thomas Gray | D24: The poetical works of Thomas Gray, ... with some account of his life and writings. The whole carefully revised; and illustrated by notes, original and selected. To which are annexed, poems written by, addressed to, or in memory of, Mr. Gray | I24: VALID_TARGET_REFERENCE | J24: HIGH | K24: DIRECT_TARGET_REFERENCE | M24: OABASEV1_b3125913f53d8a90 | N24: W000030513 | O24: W7042655948
A25: 45 | B25: Following the Equator | C25: Mark Twain | D25: The writings of Mark Twain / | E25: 1-2. The innocents abroad; or, The new Pilgrim's progress.--3-4. Roughing it.--5-6. The gilded age, a tale of to-day, by Mark Twain ... and Charles Dudley Warner.--7. Sketches, new and old.--8. The adventures of Tom Sawyer.--9-10. A tramp abroad.--11. The prince and the pauper; a tale for young people of all ages.--12. Life on the Mississippi.--13. The adventures of Huckleberry Finn.--14. A Connecticut Yankee in King Arthur's court.--15. The American claimant, and other stories and sketches.--16. Pudd'nhead Wilson and those extraordinary twins.--17-18. Personal recollections of Joan of Arc, by the Sieur Louis de Conte [pseud.] ... tr. out of the ancient French ... by Jean François Alden [pseud.]--19. Tom Sawyer abroad; Tom Sawyer detective; and otherstories, etc.--20-21. Following the equator; a journey around the world.--22. In defense of Harriet Shelley, and other essays.--23. The man that corrupted Hadleyburg, and other essays and stories.--24. The 30,000 bequest, and other stories.--25. Christian science, with notes containing correcitons to date.--26. What is man? and other essays.--27. The mysterious stranger, and other stories.--28. Mark Twain's speeches.--29. Europe and elsewhere.--30-33. Mark Twain, a biography. The personal and literary life of Samuel Langhorne Clemens, by Albert Bigelow Paine.--34-35. Marks Twain's letters, arranged with comment by Albert Bigelow Paine.--36-37. Mark Twain's autobiography. | I25: VALID_TARGET_REFERENCE | J25: HIGH | K25: DIRECT_TARGET_REFERENCE | L25: 全集目次中に "Following the equator" を明記 | M25: OABASEV1_98db6d40750c6b85 | N25: W000022689 | O25: W6997388695
A26: 46 | B26: Rogue Male | C26: Geoffrey Household | D26: "Occult Sympathy": Geoffrey Household's Watcher in the Shadows and Dance of the Dwarfs | E26: Drawing on the Edwardian adventure tale's theme of hunter and hunted exemplified by John Buchan's The Thirty-Nine Steps (1915), Geoffrey Household's Rogue Male (1939), his best-known thriller, dramatizes the exploits of an unnamed narrator who, after unsuccessfully attempting to assassinate an unspecified Central European demagogue, is literally run to ground in the Dorset countryside. A belated sequel titled Rogue Justice (1982) christens this persona Raymond Ingelram, fictionally the descendant of fifteen British generations whose aristocratic standing has been marginalized by interwar upheavals in the social order.1 Of immediate interest, though, is what transpires at the end of Rogue Male. After eleven days of being besieged in his subterranean redoubt by pseudonymous Major QuiveSmith, an anglicized Nazi agent, Ingelram contrives ballista and kills his adversary by impaling him with an iron spike. Noticing their facial resemblance, the displaced representative of English nobility then alters his appearance to replicate the photographic image in QuiveSmith's forged passport and thereby ensure his departure from the United Kingdom disguised as Latin American gentleman still intent on completing his earlier mission (181).Such plot-driven (re)doubling differs from the familiar nineteenthcentury topos of the Doppelganger. In James Hogg's The Private Memoirs and Confessions of Justified Sinner (1824), Fyodor Dostoevsky's The Double (1846), and Robert Louis Stevenson's The Strange Case of Dr. Jekyll and Mr. Hyde (1886), to cite only few novels, the projected other inversely mirrors the putative self. Narratives of this kind usually introduce us early on to the operative binary and its reversal, thereby proving fertile texts for psychoanalytic critics.2Things are less predictable, however, in the modern thriller. We thus do not discover until Rogue Male's denouement that its protagonist is prepared to abandon his ancestral identity for Quive-Smith's fraudulent impersonation or that, once he has adopted the ruse, Ingelram will pursue again his appointment with destiny. The governing dynamic of this mode of fiction, consequently, is far removed from the orientation of Erskine Childers's The Riddle of the Sands (1903) in which we encounter valorized emblems of Britannia's inevitable triumph over the combined forces of darkness. Dispensing with such reductive polarities, the genre of the thriller as we know it today first flourished during the 1930s when, in the aftermath of World War I, former constructs of inviolability such as the morally unassailable nation-state, universally shared codes of value, and an integrated, perspicuous self were rapidly unraveling.3 The best of Household's books reflect these changes while sometimes explicitly framing them in relation to manifestations of Edwardian stability.His character Raymond Ingelram, for example, deviates from such Clubland heroes as Buchan's Richard Hannay and Childers's Arthur H. Davies in two important ways.4 First, whereas Rogue Male depicts him as a bored and wealthy Englishman in the mold of Hannay (1), Rogue Justice casts Ingelram as the offspring of British father and Austrian mother, no doubt in part to account for how his bilingual fluency facilitates his reentry into the Third Reich. But beyond such practical considerations Household seems committed in several of his productions to denationalizing their protagonists, as though to intimate the obsolescence of ethnocentric or chauvinistic justifications for individual action. The second difference is that the first-person narrator of both Rogue Male and Rogue Justice figures as moral casualty haunted by his wartime experience. Household's 1939 novel suggests that this trauma is linked not only to Ingelram's torturous ordeal after his initial capture but also to subsequent crisis of conscience because his assassination attempt was motivated by the Fascists' murder of his fiancee. … | F26: 2012.0 | G26: 2012-05-01 | I26: VALID_TARGET_REFERENCE | J26: HIGH | K26: DIRECT_TARGET_REFERENCE | M26: OABASEV1_4d168835b7f5df31 | N26: W000021044 | O26: W2600546473
A27: 47 | B27: Charles Lamb | C27: Charles Lamb | D27: Lear’s Mind | E27: The greatness of Lear is not in corporal dimension, but in intellectual: the explosions of his passion are terrible as a volcano: they are storms turning up and disclosing to the bottom that sea, his mind, with all its vast riches. It is his mind which is laid bare … while we read [the tragedy] we see not Lear, but we are Lear, — we are in his mind. (Charles Lamb)1 These keywords were added by machine and not by the authors. This process is experimental and the keywords may be updated as the learning algorithm improves. | F27: 2002.0 | G27: 2002-01-01 | H27: https://doi.org/10.1057/9780230503038_7 | I27: VALID_TARGET_REFERENCE | J27: HIGH | K27: DIRECT_TARGET_REFERENCE | L27: 著者名ターゲット：Lambの Lear 論の引用（一次資料） | M27: OABASEV1_8e26fcdf4369de81 | N27: W000030490 | O27: W2500452646
A28: 48 | B28: Xi you ji | C28: Wu Cheng'en | D28: 西遊眞詮 : [一百回 / 陳士斌詮解] [volume 7] | E28: The Journey to the West (Xi you ji 西遊記), one of the Four Great Classical Novels of Chinese literature, is a supernatural novel adapted from a travel account entitled The Great Tang Records on the Western Regions (Datang xiyu ji 大唐西域記) and composed by the renowned Buddhist master Xuanzang 玄奘 (c. 602-664) of the Tang dynasty. Xuanzang took a historical trip from China to India from 629 to 645, intending to obtain Buddhist scriptures written in the original Sanskrit language. Wu Cheng'en 吳承恩 (c. 1500-c.1582), a Ming novelist and poet, is generally acknowledged as the author of The Journey to the West, who added mythical and legendary figures, such as Monkey King (孫悟空), Xuanzang's first and most artful and powerful disciple. USC's copy is a popular commentary edition from the early Qing dynasty, annotated and abridged by the critic Chen Shibing 陳士斌 (active 17th century; literary name 號 Wuyizi 悟一子), along with an additional commentary by Jin Shengtan 金聖歎 (1608-1661), a prominent literary critic and writer of the late Ming and early Qing periods. Title from container. Double leaves, oriental style, wrire-bound. Kangxi bing zi (35 nian) [1696] zhong qiu Xi tang lao ren you tong zhuan "Xi you zhen quan xu". "Mingzhi gong yi nian qiu tie zhi xiu bu"--Cover page. | F28: 2021.0 | G28: 2021-01-01 | H28: https://doi.org/10.25549/crbm-ouc113007433 | I28: VALID_TARGET_REFERENCE | J28: HIGH | K28: VALID_TITLE_VARIANT | L28: 西遊記の清代注釈版（西遊真詮）。同一作品 | M28: OABASEV1_3c10ec371a36d353 | N28: W000017051 | O28: W7104272792
A29: 49 | B29: Galen | C29: Galen | D29: Endoscopic Third Ventriculostomy With Choroid Plexus Cauterization Application in the Management of Hydrocephalus in Previously Embolized Vein of Galen Malformations: 2-Dimensional Operative Video | F29: 2026.0 | G29: 2026-02-04 | H29: https://doi.org/10.1227/ons.0000000000001915 | I29: INVALID_TARGET_REFERENCE | J29: HIGH | K29: GENERIC_OR_LEXICAL_TITLE_USE | L29: "Vein of Galen malformation"（解剖学上の名祖） | M29: OABASEV1_eeaba92b82f73015 | N29: W000031472 | O29: W7127635117
A30: 50 | B30: Mrs. Dalloway | C30: Virginia Woolf | D30: A Feminist Perspective Of Virginia Woolf''s Selected Novels :, Mrs, Dalloway And To The Lighthouse | F30: 2004.0 | G30: 2004-01-01 | H30: https://doi.org/10.34065/1262-008-001-006 | I30: VALID_TARGET_REFERENCE | J30: HIGH | K30: DIRECT_TARGET_REFERENCE | M30: OABASEV1_fe29d6729041143d | N30: W000018010 | O30: W4411806711

Sheet Audit 03
A1: OpenAlex R2+A1 Blind Human Audit — R2A1A03
A2: 判定対象：OpenAlex record が target literary work を本当に参照しているか。LLM判定・sampling stratum・risk featureは非表示です。Web検索はしません。
A4: 入力欄 → | I4: Judgment | J4: Confidence | K4: Reason | L4: Reviewer note
A5: Review # | B5: Target title | C5: Target author | D5: OpenAlex record title | E5: OpenAlex abstract | F5: Year | G5: Publication date | H5: DOI | I5: Judgment | J5: Confidence | K5: Reason | L5: Reviewer note | M5: Candidate ID | N5: Project Work ID | O5: OpenAlex Work ID
A6: 51 | B6: Henry James | C6: Henry James | D6: Homes and Homelessness in the Victorian Imagination | E6: The essays in this volume deal centrally with Dickens's images of homelessness, but also with those of other Victorians also - Disraeli, Mrs Gaskell, Israel Zangwill, John Ruskin and Henry James. The issues addressed by these Victorians are the same as those we face today. | F6: 2001.0 | G6: 2001-01-01 | H6: https://doi.org/10.2307/3509424 | I6: VALID_TARGET_REFERENCE | J6: HIGH | K6: VALID_CONTEXTUAL_REFERENCE | L6: 著者名ターゲット：Victorian作家としてHenry Jamesの作品を扱う | M6: OABASEV1_022e51a1e6c6a919 | N6: W000014024 | O6: W2072025588
A7: 52 | B7: Henry James | C7: Henry James | D7: The Marriage Paradox: Modernist Novels and the Cultural Imperative to Marry (review) | E7: Reviewed by: The Marriage Paradox: Modernist Novels and the Cultural Imperative to Marry Victor Luftig The Marriage Paradox: Modernist Novels and the Cultural Imperative to Marry. Davida Pines . Gainesville: University Press of Florida, 2006. Pp. x + 157. $59.95 (cloth). "The marriage plot is inescapable," Davida Pines begins by announcing. To those of us, such as Rachel Blau DuPlessis, Joseph Boone, and Anne de Cille, who have described modernist novels as offering hostility, resistance, and alternatives to marriage, Pines responds that we have insufficiently acknowledged not just the sturdiness of the institution but modernist fiction's complicity in shoring it up. Chapters devoted to works by Henry James, Ford Madox Ford, D. H. Lawrence, Nella Larsen and Zora Neale Hurston, and Virginia Woolf each analyze apparently disruptive experiments that only ratify the marital impulse. "While the novels I examine offer a relentless critique of the marriage relationship and of the social imperative to marry," Pines says, "the works paradoxically reinforce the marital norm" (3). [End Page 367] Thus, though Portrait of a Lady exposes the forces that compel women to marry, it nevertheless leaves marriage as the sole vehicle for fulfillment of personal desire: "the marriage plot offers," the chapter concludes, "the only way out" (32). Likewise, in spite of relentless ironies and ambiguities revolving around "the discourse of marital failure" (46) in The Good Soldier and Parade's End, "the institution itself remains in place" (54). The attempt of Ursula and Birkin in Women in Love to "transcend marriage" through sexual experimentation "only reinforces its societal hold" (75). Modernist novels by black women writers, such as Quicksand and Their Eyes Were Watching God, "unwittingly reinforce the very institution they intend to critique" (78), because, like Portrait of a Lady, they rely on romantic paradigms of self-fulfillment. And for all the energy that Between the Acts puts towards distinguishing nature from culture, "the novel effectively naturalizes marriage" (96), suggesting a "heterosexual imperative" at the heart of "the cultural construction of the marriage plot" (113). One reason why these novels never shatter the institutional norm is that they are, like much modernist art, resolutely individualist in their priorities. Pines's critique of this emphasis reaches its greatest intensity midway through her chapter on Larsen and Hurston: "As I have argued throughout the book . . . focusing on individuals rather than societal scripts, couples rather than the institution itself, inevitably leads to a reproduction of the status quo" (80). The Marriage Paradox has the feeling of a self-fulfilling prophecy not just in its repeated and dispiriting recognition of such capitulations but also in its own fascination with couples and their personal crises. While Pines includes intermittent references to Victorian and early twentieth-century legal and cultural debates about marriage and divorce, most of the book's energy is focused on intense readings within the marriage plots themselves. Concluding the James chapter with her insistence that marriage is "the only way out" for Isabel and Pansy, Pines cleverly tempts us to ask "'Out' of what?," in order to make us accept the answer "Marriage" and thus to accept her notion of a "paradox." But one can still wish that the chapter had said more about the economic and cultural constraints surrounding marriage that bind the female characters and the realist plot. Though Pines faults the modernist novel for thinking too small, for focusing on individuals rather than the institution, she neglects opportunities to think about structures larger than marriage and especially about why novels and characters seem so insistently drawn to it. An implicit answer is suggested by the very fine chapter on Woolf and then by the smart, expansive conclusion. Pines persuasively reads the treatment of marriage in Between the Acts in relation to the advent of the Second World War; that approach necessarily reminds one that earlier chapters had focused on the First World War novels by Ford and Lawrence and that her Larsen-Hurston chapter had underscored the vulnerability of African-American families before and after emancipation: "While slaves might fall in love, that love was meaningless, nonexistent, under the law. Without legal sanction, families simply disappeared" (80). What most of Pines's chosen novels have in common, then, is... | F7: 2007.0 | G7: 2007-04-01 | H7: https://doi.org/10.1353/mod.2007.0042 | I7: VALID_TARGET_REFERENCE | J7: HIGH | K7: DIRECT_TARGET_REFERENCE | L7: 著者名ターゲット：Portrait of a Lady を扱う章 | M7: OABASEV1_201920dc1f76fd58 | N7: W000014024 | O7: W2085872073
A8: 53 | B8: Josephus | C8: Flavius Josephus | D8: Bibliothek der griechischen und romischen schriftsteller uber judenthum und Juden ... | E8: v. 1. Das leben Mosis von Philo dem Alexandriner.--v. 2. Die kleineren schriften des Flavius Josephus.--v. 3. Philo des Alexandriners gesammelte schriften.--v. 4. Ueber die opfer Abel's und Kains's; Ueber die nachtsellungen, die das schlechtere dem besseren zu bereiten pflegt; Ueber die sprösslinge des sich weise dünkenden Kain, und wie er ein flüchtling wird; Ueber die riesen; Ueber die unveränderlichkeit Gottes; Verzeichnisz der citirten Bibelstellen. | I8: VALID_TARGET_REFERENCE | J8: HIGH | K8: DIRECT_TARGET_REFERENCE | L8: 著者名ターゲット：Josephusの小著作集 | M8: OABASEV1_c9c71cac4436812a | N8: W000004772 | O8: W6980247826
A9: 54 | B9: A House of Pomegranates | C9: Oscar Wilde | D9: Salomé ; A florentine tragedy ; and, Vera | E9: The Duchess of Padua 224pp Salome, A Florentine Tragedy and Vera 272pp Lady Windermere's Fan 198pp A Woman Of No Importance 206pp An Ideal Husband 254pp The Importance Of Being Earnest 202pp Lord Arthur Savile's Crime and Other Pieces 274pp Intentions and The Soul of Man 344pp Poems 358pp A House of Pomegranates and Other Tales 266pp De Profundis 230pp The Picture of Dorian Gray For Love of the King [1922] 426pp Reviews 572pp Miscellanies 362pp Bibliography of Oscar Wilde [1914] Stuart Mason 640pp illustrated | F9: 1993.0 | G9: 1993-01-01 | I9: VALID_TARGET_REFERENCE | J9: HIGH | K9: DIRECT_TARGET_REFERENCE | L9: 全集目録中に明記 | M9: OABASEV1_5b68be2ff4fd0fd4 | N9: W000004062 | O9: W650702868
A10: 55 | B10: Henry James | C10: Henry James | D10: Philip Roth's Rude Truth: The Art of Immaturity (review) | E10: Reviewed by Ranen Omer-Sherman University of Miami Philip Roth's Rude Truth: The Art of Immaturity. Ross Posnock. Princeton, NJ: Princeton University Press, 2006. Pp. xx + 301. $29.95 (cloth). In recent years, there have been a number of very worthy book-length studies of Philip Roth, including Elaine Safer's Mocking the Age: The Later Novels of Philip Roth (2006), Debra Shostak's Philip Roth—Countertexts, Counterlives (2004), and Mark Shechner's Up Society's Ass, Copper: Rereading Philip Roth (2003). Comprehensive volumes of essays addressing Roth's [End Page 592] entire oeuvre have also lately appeared: Tim Parrish's The Cambridge Companion to Philip Roth (2007) and Derek Parker Royal's Philip Roth: New Perspectives on an American Author (2005). In the light of this prolific scholarship (much of it exemplary), it is important to state at the outset that Ross Posnock's study may be the most intellectually complex as well as fiercely independent study of Roth's career to date. At its very best, Posnock's intellectually and imaginatively resonant study of "the art of immaturity" can seem both astonishing and somehow absolutely right. Filled with deft observations, this critical study offers authoritative readings of literature and society which have profound implications that exceed considerations of Roth, its ostensible solitary subject. A staunch Americanist, Posnock's previous works include books on Henry and William James as well as important essays on Ralph Ellison and other African American writers. But here he exhibits a breathtaking ease with an eclectic range of figures (the Frankfurt school, numerous East European writers) that enables him to firmly situate Roth in the cosmopolitan tradition in ways that will likely have a lasting influence on Roth scholarship. In essence, Posnock explains in an elegant formulation that "immaturity" serves the artist as "a vehicle for the exploration of moral fantasy" (38). In the context of Roth's novels, he sees this paradigm expressed through variations on the following: "Freedom from being the good boy, freedom to discover and sublimate in art the anarchic and unsocialized parts of the self—all this requires an undoing of 'maturity,' a wounding of the responsible adult self . . . This process of letting go or undoing defenses defines Roth's creative economy" (38). Posnock is wonderfully attuned to the fact that, especially in Eastern Europe, a milieu that has had a powerful impact on Roth's skeptical imagination, creative immaturity also has profound political stakes, expressing its perverse resistance to totalitarian culture through "love of agonistic combat and rude truth" (9). It staunchly refuses "utopian thinking" and the illusions of "pastoral and idylls" in all their regressive forms. Posnock's introductory chapter begins brilliantly, casting us immediately into the soaring cadences of one of Roth's characters' uninhibited litanies of outrage, as if to establish his sheer pleasure in the novelist's verbal exuberance. Like most Roth critics of late, Posnock is suitably impressed by the fact that, unlike the oeuvres of so many major novelists whose late works lack the ambition and energy of their best days, Roth's most powerful works have emerged in his later years: "This is unprecedented . . . Roth is now beginning to deserve comparison with what is usually regarded as the summit of late turns of novelistic genius—Henry James's major phase at the start of the century" (5–6). In this chapter, Posnock takes immaturity very seriously indeed, cogently tracing its surprising and subversive cultural permutations from the Renaissance through early modernism up until the contemporary novel. At the same time, sensitive to the fact that the privileges of "immaturity" have considerable gender implications (since it is generally allied with a masculinist avant-garde temperament), the author zealously defends Roth against enduring charges of misogyny, pointing out the "depth of characterization" apparent in a wide range of important female protagonists, including Lucy Nelson of the underrated early novel When She Was Good, Michelle Cowan in Sabbath's Theater, and the poignant figure of Faunia Farley in The... | F10: 2007.0 | G10: 2007-09-01 | H10: https://doi.org/10.1353/mod.2007.0069 | I10: VALID_TARGET_REFERENCE | J10: HIGH | K10: VALID_CONTEXTUAL_REFERENCE | L10: 著者名ターゲット：Henry Jamesの研究書と「major phase」への言及 | M10: OABASEV1_35f9666f60ad2bc4 | N10: W000014024 | O10: W2060694246
A11: 56 | B11: Heart of Darkness | C11: Joseph Conrad | D11: BOOK REVIEW: Peter Edgerly Firchow.ENVISIONING AFRICA: RACISM AND IMPERIALISM IN CONRAD'SHEART OF DARKNESS, Lexington: U of Kentucky P, 2000. | E11: More than 25 years have passed since Chinua Achebe called Joseph Conrad a "bloody racist," and the scholarly world has yet to recover. Scarcely a year goes by without another earnest attempt to soften or rebut Achebe's charges, generally by the judicious invocation of historical context. Achebe himself has stood by the offending comment, even as an entire industry of postcolonial studies has grown up to reiterate the claim in more theoretically polite terms. Achebe's essay, "An Image of Africa," has by now attained a canonical status of its own, being regularly anthologized and invoked whenever discussion turns to Conrad's 1899 novella. Whatever one's ultimate judgment of "Heart of Darkness" itself, Achebe's remark had the decided merit of restoring what Edward Said calls the "worldliness" of the text--its powerful, messy, disturbed and even harrowing implication in the shameful violence of European imperialism. Expelled from the hushed precincts of the modernist pantheon, Conrad's text--despite, or perhaps thanks to, Achebe's intervention--retains an actuality that other masterpieces from the turn of the last century can only envy. | F11: 2001.0 | G11: 2001-03-01 | H11: https://doi.org/10.2979/ral.2001.32.1.129 | I11: VALID_TARGET_REFERENCE | J11: HIGH | K11: DIRECT_TARGET_REFERENCE | M11: OABASEV1_2dbf42bcc67cbd6b | N11: W000014272 | O11: W1985393133
A12: 57 | B12: Dead yellow women | C12: Dashiell Hammett | D12: Scorched Earth: Expressions of Modernity in Dashiell Hammett's Pulp Fiction | E12: Samuel Dashiell Hammett (“Dash”), American author and activist, is today best known for one of the novels he published 1930, The Maltese Falcon. My thesis presents evidence that a close study of a selection of Hammett’s short stories and novels published between 1925 and 1930 (“Dead Yellow Women,” “The Scorched Face,” “The Gutting of Couffignal,” Red Harvest, and The Maltese Falcon) exposes his personal struggle with modernity in America, through a discussion of three motifs. In his stories and novels, Hammett explores the fluctuating treatment of immigrants, and changing social spaces for newly independent women in post-World War I America. He also questions the consequences of increasing mechanization in cities, through everyman detectives Sam Spade and the Continental Op. As Hammett’s career progresses, he continues to passionately challenge the benefits of conservative cultural values, while urging caution against the unreserved embrace of modernism.\nResearch for this paper originated with a close study of Hammett’s letters, and several biographies (including Layman and Ward). A range of critics contributed to a discussion of Hammett as a modernist author (e.g. Wheat and Norman). Articles on post- World War I literature were also essential to my research (e.g. Tate and Stevenson). A review of the available material demonstrated the need to analyze Hammett’s complex relationship with modernity, and how the bond evolved over time. While Hammett establishes specific motifs early in his career, it is not until 1930 that he standardizes his unique portrayal of modernism in American cities, and urges readers to approach modernism in America with cautious optimism. | F12: 2018.0 | G12: 2018-02-09 | I12: VALID_TARGET_REFERENCE | J12: HIGH | K12: DIRECT_TARGET_REFERENCE | M12: OABASEV1_f292faa21879ae35 | N12: W000019540 | O12: W2907215993
A13: 58 | B13: Murder on the Orient Express | C13: Agatha Christie | D13: THE POETICS OF NARRATIVE UNRELIABILITY AND READER MISDIRECTION IN THE WORKS OF AGATHA CHRISTIE | E13: This article provides a comprehensive analysis of narrative unreliability and the poetics of reader misdirection in the works of Agatha Christie (1890–1976), the celebrated British detective fiction writer. Drawing on Aristotle’s theory of mimesis, Wayne C. Booth’s concept of the unreliable narrator, and Gérard Genette’s narratology as theoretical frameworks, the study examines four major Christie novels — The Murder of Roger Ackroyd (1926), And Then There Were None (1939), Murder on the Orient Express (1934), and Crooked House (1949). The article identifies and analyses key narrative mechanisms including the red herring technique, selective silence, unreliable focalization, and metatextual deception. Christie’s strategy of subverting genre conventions is further assessed from a literary-philosophical perspective. The conclusion argues that narrative unreliability in Christie’s fiction functions not merely as a genre device, but as an epistemological challenge that interrogates the very nature of truth and the limits of human cognition. | F13: 2026.0 | G13: 2026-06-01 | H13: https://doi.org/10.5281/zenodo.20484155 | I13: VALID_TARGET_REFERENCE | J13: HIGH | K13: DIRECT_TARGET_REFERENCE | M13: OABASEV1_4bb9a78f412722ad | N13: W000020866 | O13: W7163032600
A14: 59 | B14: Le docteur Pascal | C14: Émile Zola | D14: La science et ses traductions espagnoles dans l'oeuvre romanesque d'Émile Zola | E14: Il s'agit d'une etude traductologique ayant comme objet la science traduite en espagnol dans les romans d'Emile Zola. Les romans etudies sont Therese Raquin, La Conquete de Plassans, l'Assommoir, La Joie de Vivre, Germinal, La Terre, La Bete Humaine et Le Docteur Pascal. | F14: 2017.0 | G14: 2017-07-18 | I14: VALID_TARGET_REFERENCE | J14: HIGH | K14: DIRECT_TARGET_REFERENCE | M14: OABASEV1_7c983bad21ec6e33 | N14: W000031720 | O14: W2767357015
A15: 60 | B15: Chaucer | C15: Geoffrey Chaucer | D15: The works of Geoffrey Chaucer, now newly imprinted | E15: Title page and 1st text page within decorative borders; ornamental initials and marginal decorations; sidenotes in red. Text in double columns; printed in Chaucer type; with the headings to the longer poems in Troy type; the whole was printed on Batchelor handmade paper watermarked with a fish. | F15: 2018.0 | G15: 2018-01-01 | H15: https://doi.org/10.14288/1.0366915 | I15: VALID_TARGET_REFERENCE | J15: HIGH | K15: DIRECT_TARGET_REFERENCE | M15: OABASEV1_2babbfb09ad566a7 | N15: W000005351 | O15: W358502991
A16: 61 | B16: Charles Lamb | C16: Charles Lamb | D16: Overview | E16: Thomas Noon Talfourd (1795–1854), the son of a Reading brewer, was better known for his activities as a literary journalist and author. As the contributor of articles of dramatic criticism to the New Monthly Magazine , he became friendly with many leading writers of the day, including William Hazlitt, Charles Lamb, Godwin’s nineteenth-century disciple Edward Bulwer, and Godwin himself. Talfourd’s retrospective account of Godwin in 1848 is very different from his earlier essay on his writings published in the New Monthly Magazine in 1820. Talfourd writes admiringly of Political Justice and declares his sympathy with its principles, even though he regrets its &s;speculative extravagance&s;. At first glance, Talfourd’s description of Godwin as ‘a man of two beings’ seems to recall Hazlitt’s various accounts of Godwin’s mixed intellectual character. Though the tone of Talfourd’s references to Godwin’s personal demeanour is largely respectful, his emphasis on his subject’s apparent imperturbability also provides a means of defusing his controversial political views. | F16: 2020.0 | G16: 2020-04-02 | H16: https://doi.org/10.4324/9780429348259-36 | I16: VALID_TARGET_REFERENCE | J16: MEDIUM | K16: VALID_CONTEXTUAL_REFERENCE | L16: 著者名ターゲット：Talfourdの交友として作家Charles Lambの名が挙がるのみ（作品言及なし） | M16: OABASEV1_d267dffd6935aeea | N16: W000030490 | O16: W4232039109
A17: 62 | B17: Galen | C17: Galen | D17: Stenting of a Venous Stenosis in Vein of Galen Aneurysmal Malformation | E17: SUMMARY: The vein of Galen aneurysmal malformation (VGAM) is a high flow arteriovenous shunt at the choroidal level. In the neonatal period, it typically presents with cardiac failure. Venous stenoses, occlusions and anomalies are often present. In the absence of adequate venous outflow pathways, severe, irreversible cerebral parenchymal damage may occur due to intracranial venous hypertension, altered hydrodynamics and ischaemia. We present a case of deployment of a stent across a focal superior jugular bulb stenosis in an effort to avert this outcome. | F17: 2001.0 | G17: 2001-09-01 | H17: https://doi.org/10.1177/159101990100700309 | I17: INVALID_TARGET_REFERENCE | J17: HIGH | K17: GENERIC_OR_LEXICAL_TITLE_USE | L17: "Vein of Galen aneurysmal malformation"（解剖学上の名祖） | M17: OABASEV1_3d5af96be24b1fc9 | N17: W000031472 | O17: W1844779822
A18: 63 | B18: Arnold | C18: Matthew Arnold | D18: Tributes or Travesties?: Recent Reworkings of Classics Great and Small | E18: What Is a ‘Classic’? The classic is memorably defined by Matthew Arnold when he refuses to define it (Arnold: 1446). For him it is the timeless universal against which all else may be measured. But as T.S. Eliot goes on to point out in ‘What is a Classic?’, a classic assumes its value as it rises in some combination of historical and cultural moments that leave it perched ark-like on a summit of achievement from which the waters of that literary tradition have receded: Virgil at the close of the Roman Empire. However, if such a work is not to moulder away, admired but untouchable in the museum of Great Works, it must be part of an ongoing culture and must be revisited, emulated, reshaped, changed, challenged. Whether we think of Harold Bloom's ‘influence’ or Edward Said's ‘iteration’, the universal timeless classic or the great literary career is only good in so far as it is also made local and part of cultural practice in history (Said: 256-257). Constant Rehearsal of Hindu Classics in the Indian Tradition Indian tradition shows this in its constant rehearsal of the Hindu classics in the literary retranslations across millennia, in folk dramas, song, painting, sculpture, film and television serials. Indian writing in English sought to authenticate itself within the post-colonial nation by reworking the traditional archive, from Toru Dutt's poems to Raja Rao's fictionalising of Puranic style and content. As it grew in self-confidence, it became less subservient to this material, putting it to use in order to make points about modern society and even showing some irreverence towards it. Thus we find Arundhati Roy in The God of Small Things both critiquing the masculinist vengeance of Mahabharata stories in contemporary Kathakali and lamenting their reduction to touristic entertainments (Roy 1997: 228-236), and Shashi Tharoor satirising the political history of modern India by parodying a wide swathe of the Mahabharata in The Great Indian Novel . Salman Rushdie likewise pays tribute to Persian Sufism in Grimus and to the Kathasaritsagara in Haroun and the Sea of Stories , the latter an allegorical critique of dictatorships in the contemporary world. | F18: 2013.0 | G18: 2013-10-15 | H18: https://doi.org/10.1017/9789048518852.007 | I18: VALID_TARGET_REFERENCE | J18: HIGH | K18: DIRECT_TARGET_REFERENCE | L18: 著者名ターゲット：Arnoldのclassic論を引用（Arnold: 1446） | M18: OABASEV1_351b51550a936ec9 | N18: W000003023 | O18: W1539283211
A19: 64 | B19: Maria Edgeworth | C19: Maria Edgeworth | D19: Novel spectators | E19: Tom Jones is a typical eighteenth-century hero: he is beaten, bullied, seduced, betrayed, and banished by numerous other characters in the narrative. He performs very little action himself, and that rather unsuccessfully. In one escapade in Book XIII, the hero overwhelmed by London society and ignored by his hosts, Fielding writes that “Poor Jones was rather a Spectator of this elegant scene, than an actor in it” (Tom Jones 451). Tom Jones is a bystander in his own story. The same might be said of protagonists like Samuel Richardson’s Clarissa Harlowe and Maria Edgeworth’s Belinda Portman—protagonists who, like Tom Jones, tend to observe more than participate in their own narratives. Belinda is remembered most for having a dry personality, while Clarissa famously spends hundreds of pages willing herself to die. For modern readers, these characters may seem to lack agency. Despite their apparent passivity, however, these characters reveal the powerful agency of spectatorship in eighteenth-century culture. The spectator figure played a newly dominant role in both the English theater and English society at large across the eighteenth century. Many writers used theatrical imagery to justify spectatorship as more than passive observation. Analyzing depictions of spectatorship in the works of authors ranging from eighteenth-century periodical writers like Joseph Addison and Richard Steele to aesthetic theorists like Adam Smith, and from artists like William Hogarth to romantic playwrights like Joanna Baillie, I show how spectatorship offered a potent form of moral authority more rooted in judgment than action. Moreover, I argue that engaged spectatorship offered an important theatrical model for protagonists in the eighteenth-century novel. | F19: 2011.0 | G19: 2011-05-01 | H19: https://doi.org/10.17077/etd.39v1bj0q | I19: VALID_TARGET_REFERENCE | J19: HIGH | K19: DIRECT_TARGET_REFERENCE | L19: 著者名ターゲット：Belinda を扱う | M19: OABASEV1_a97cd4e663eb3737 | N19: W000031690 | O19: W387835447
A20: 65 | B20: Henry James | C20: Henry James | D20: Wilde's comedies of Society | E20: Wilde's three Society comedies were produced by different managers: Lady Windermere's Fan by George Alexander at the St James's Theatre (20 February 1892), A Woman of No Importance by Herbert Beerbohm Tree (19 April 1893) and An Ideal Husband (3 January 1895) by Lewis Waller, both at the Theatre Royal, Haymarket. Had Henry James's Guy Domville not been a failure and left Alexander with a gap in his season, Wilde would have added Charles Wyndham and the Criterion Theatre to his list with The Importance of Being Earnest. In the months before his career collapsed in the witness box of the Queensberry libel trial, he was sketching out a new play of modern life for Alexander, the Gerald Lancing scenario which Frank Harris later fleshed out as Mr and Mrs Daventry; and negotiating with American producers such as Albert Palmer about a play ' “with no real serious interest” - just a comedy', and with Charles Frohman for a 'modern “School for Scandal”' style of play. This flurry of activity indicates both Wilde's perceived marketability on both sides of the Atlantic and his own growing confidence in a genre he had only taken up in 1891, in fact at Alexander's invitation. 'I wonder can I do it in a week, or will it take three?' he reportedly commented to Frank Harris. 'It ought not to take long to beat the Pineros and the Joneses.' Writing to Alexander in February 1891, Wilde offered a rather different attitude towards his progress on Lady Windermere's Fan : 'I am not satisfied with myself or my work. I can't get a grip of the play yet: I can't get my people real... I am very sorry, but artistic work can't be done unless one is in the mood; certainly my work can't. Sometimes I spend months over a thing, and don't do any good; at other times I write a thing in a fortnight' ( L 282). | F20: 1997.0 | G20: 1997-10-16 | H20: https://doi.org/10.1017/ccol052147471x.010 | I20: VALID_TARGET_REFERENCE | J20: HIGH | K20: DIRECT_TARGET_REFERENCE | L20: 著者名ターゲット：Guy Domville への言及 | M20: OABASEV1_8b0fe3b5f803e6e7 | N20: W000014024 | O20: W2972130145
A21: 66 | B21: Steinbeck | C21: John Steinbeck | D21: Of Mice and Men: The Tale of Steroidogenic Factor-1 | E21: In John Steinbeck’s famous novel, George and Lennie dream of a simple bucolic life, living on a ranch in southern California (1). However, as foreshadowed by the poem on which the title is based, their best-laid plans go awry. In medicine, we harbor similarly simplistic views of the world, if for no other reason than to bring order to complex physiological events or to provide a framework for testing ideas. More often than not, these models are incomplete, if not altogether wrong. Nonetheless, this hypothesis-driven approach is the foundation of our scientific method. In this editorial, I will highlight the interplay between genetic models in mice and our understanding of inherited reproductive disorders in man, focusing on recent findings involving steroidogenic factor-1 (SF-1). Increasingly, mouse models help to unravel complex physiological pathways, including the regulation of reproduction (2). Genetic studies in humans historically have been based on testing candidate genes or performing linkage studies, which are rarely applicable when reproduction is compromised. Mice provide an opportunity for performing targeted mutagenesis, including knockout and knock-in approaches, as well as transgenic expression of genes (3). More recently, ethylnitrosourea and transgenic insertional mutagenesis enable “forward genetic” approaches that use phenotypic screens to identify novel genes (4). Although we often focus on the differences in mouse and human phenotypes caused by mutations in homologous genes, it is notable that different inbred strains of mice also differ considerably in the phenotypic expression of traits; this feature potentially allows the identification of modifier genes in mice of different genetic backgrounds (5). A few examples in the field of reproduction illustrate the conceptual advantages conferred by parallel studies in humans and in mice. This year, a report described hypogonadotropic hypogonadism caused by mutations in GPR54, a G protein-coupled seven-transmembrane receptor proposed to regulate puberty and gonadotropin production (6). Linkage studies and mutational analyses in humans were accompanied by characterization of a GPR54 knockout mouse, providing independent lines of evidence that this receptor plays a key role in reactivation of the GnRH pulse generator (6, 7). The DAX1 (dosage-sensitive sex reversal-adrenal hypoplasia congenita critical region on the X chromosome, gene 1) gene was identified in humans with X-linked adrenal hypoplasia congenita and hypogonadotropic hypogonadism. A Dax1 knockout model in mice revealed a primary testicular defect that had been unrecognized in humans because of concomitant gonadotropin deficiency (8, 9). A series of recent reports on SF-1 mutations in humans reveal a surprisingly broad spectrum of phenotypic features (10–15) and underscore the dose-dependent action of SF-1. What were the critical steps that brought us to this level of understanding? SF-1 (also known as adrenal 4-binding protein, Ad4BP) was originally identified as a transcription factor that binds to DNA regulatory elements in the proximal promoter regions of steroidogenic enzyme genes (16). In fact, SF-1 is considered a master regulator of reproduction, because its targets include genes at every level of the hypothalamic-pituitary-gonadal axis, as well as most genes involved in gonadal and adrenal steroidogenesis. The cloning of bovine and mouse genes encoding Sf-1 revealed that it resembled the Drosophila orphan nuclear receptor, fushi tarazu factor-1 (Ftz), a gene involved in segmentation. The human SF-1 gene (officially designated NR5A1) encodes a 461-amino-acid protein that shares structural similarities with members of the nuclear receptor superfamily. Like other nuclear receptors, SF-1 binds to specific DNA sequences in target genes and regulates transcription. Specifically, it binds to DNA as a monomer and recognizes variations of the DNA sequence motif, T/CCA AGGTCA (17). In most cases, SF-1 functions cooperatively with other transcription factors to modulate the timing and level of gene expression. It is this cooperative interaction with other factors that allows it to regulate so many target genes, which differ widely in their expression patterns and regulation. Critical structural regions in SF-1 include a zinc finger DNA binding domain, an “A” box (or FTZF1 box) accessory DNA-binding domain, a hinge region, and an activation function-2 domain involved in transcriptional control. Unlike many classical nuclear receptors, such as the estrogen, glucocorticoid, or thyroid hormone receptors, there is no known ligand that regulates SF-1-mediated transcription. Consequently, it is classified as an orphan nuclear receptor to recognize the possibility that a ligand may yet be discovered. It is possible, however, that SF-1 is regulated independently of a specific ligand; its pattern and level of expression, interaction with other transcription factors, or posttranslational modifications represent plausible means to control its action (18). In the absence of a known ligand, how does one determine its physiological role? A first step is to characterize when and where SF-1 is expressed, potentially predicting possible functions. In the mouse, Sf-1 is first expressed in the urogenital ridge at embryonic d 9 (e9) (19). After gonadal determination (e13), Sf-1 is expressed in a population of rapidly proliferating cells in the developing testis (20). In Sertoli cells, Sf-1 regulates Müllerian inhibiting substance expression, leading to regression of Müllerian structures in males. In Leydig cells, Sf-1 regulates the steroidogenic enzyme genes that control testosterone biosynthesis. Sf-1 also plays an important role in the normal development and function of the hypothalamic-pituitary-gonadal axis. It is expressed in the ventral medial hypothalamus (VMH) and in pituitary gonadotropes. Thus, Sf-1 regulates an enormous number of genes involved in sex determination and differentiation, reproduction, and steroidogenesis (16). The physiological role of Sf-1 was clearly established by generating knockout mice (21), which were found to have adrenal and gonadal agenesis. The XY mice exhibit male-to-female sex reversal, including persistent Müllerian structures, reflecting the absence of fetal androgens and Müllerian inhibiting substance. The knockout mice also have decreased levels of gonadotropins and a near absence of the VMH. Gonadotrope function could be restored by GnRH treatment, suggesting that Sf-1 deficiency does not result in an complete loss of gonadotrope cell function. These striking phenotypic features in Sf-1-deficient mice generated considerable interest because they demonstrated that orphan nuclear receptors might play important developmental roles. Targeted mutagenesis of Sf1 has now been performed in the VMH, gonadotropes, and Leydig cells, confirming its intrinsic function in these tissues (22). The mouse Sf-1 knockout phenotype prompted studies of humans with combined adrenal and gonadal defects for possible mutations in SF-1 (10). There are now five reported human SF-1 mutations, including two reports in recent issues of The Journal of Clinical Endocrinology & Metabolism (14, 15). Each new case provides important insight into the physiological role of SF-1 and clarifies the phenotypic spectrum associated with SF-1 mutations (see Table 2 in Ref.14). The first human SF-1 mutation (G35E) was described in a patient with primary adrenal failure, XY sex reversal and persistent Müllerian structures (10), thereby exhibiting features very similar to the knockout mouse. Unexpectedly, however, DNA sequencing revealed a heterozygous mutation in the DNA binding domain. Thus, in humans, a heterozygous mutation in SF-1 appeared to cause the same phenotypic consequences as complete deficiency of Sf-1 in the mouse. These clinical effects were thought to primarily result from a loss-of-function effect, although it is difficult to exclude the possibility that the mutant protein exerts some degree of dominant negative activity, inhibiting the function of SF-1 expressed from the normal allele (23). The concept of dose-dependent action of SF-1 was reinforced by the second reported case, also an XY female with adrenal insufficiency. This patient was homozygous for an SF-1 mutation (R92Q) that only partially impaired DNA binding (11). Of note, three heterozygous relatives (both parents and a sibling) were clinically normal, with no evidence of adrenal insufficiency or reproductive dysfunction. Thus, this milder SF-1 mutation did not cause phenotypic effects unless transmitted on both alleles. Two recently reported cases describe patients with heterozygous SF-1 mutations that generate null alleles since almost all of the protein is missing (14, 15). Both of these XY individuals have testicular dysgenesis but normal adrenal function. Similarly, an XY patient with a heterozygous mutation reported to exert dominant negative activity, had testicular regression but normal adrenal function (13). These patients differ in the extent of virilization and regression of Müllerian structures, suggesting variability in Leydig and Sertoli cell function. Thus, in humans, the testis may be more sensitive to loss of SF-1 function than the adrenal gland, or the adrenal gland may have a greater capacity to undergo compensatory growth and function. Of note, these gland-specific sensitivities are different in heterozygous Sf-1 knockout mice; testis development is relatively normal but the mice have adrenal hypoplasia and blunted stress-induced cortisol responses (24, 25). Only one SF-1 mutation has been reported in a prepubertal XX individual who presented with adrenal insufficiency (12). Although there was evidence that ovarian tissue was present, the consequences of the SF-1 mutation on adult ovarian function are currently unknown. When confronted with patients who have adrenal insufficiency and gonadal dysfunction, the differential diagnosis has become surprising broad. Hypopituitarism can usually be excluded based on routine hormone testing. Mutations in STAR (steroidogenic acute regulatory protein) are recessive and cause lipoid adrenal hyperplasia (26). XY subjects have adrenal insufficiency and Leydig cell failure because of defective cholesterol transport and toxic accumulation of lipid precursors, resulting in undervirilized or female genitalia. XX individuals have adrenal dysfunction and impaired ovarian function but relatively normal feminization because ovarian steroid synthesis is preserved initially and the accumulation of steroid precursors is reduced because follicle development is critical (26). The phenotype of patients with STAR mutations is similar to those with mutations in CYP11A1 (side-chain cleavage enzyme), which cause a block in the synthesis of all downstream steroids (27). Mutations in DAX-1 cause X-linked adrenal hypoplasia congenita, which is characterized by adrenal insufficiency, hypogonadotropic hypogonadism, and testicular dysgenesis (9). As noted above, mutations in SF-1 cause a phenotypic spectrum that can include variable degrees of adrenal insufficiency and testicular dysgenesis. The recent observation that some patients with SF-1 mutations have testicular dysgenesis without adrenal insufficiency raises the issue of which genetic abnormalities should be considered in XY patients with gonadal dysgenesis. Some of this population will have Klinefelter’s syndrome (XXY and variants); others may have XO/XY mosaicism. In principle, many genes involved in testis determination and differentiation are candidates for causing XY testicular dysgenesis (28). Mutations in sex-determining region on the Y chromosome preempt testis development but only account for about 10–15% of cases of XY sex reversal (29). Mutations in Wilm’s tumor-1 or Sry-related high mobility group box cause gonadal dysgenesis but are also associated with renal or skeletal abnormalities, respectively. Duplications of WNT4 (wingless-type mouse mammary tumor virus integration site family, member 4), or DAX1 can cause testis dysgenesis. Genes involved in Leydig cell development [DHH (Desert Hedgehog), ARX (Aristaless-related homeobox, X-linked), LHCGR (LH receptor)], or androgen synthesis (STAR, CYP11A1, CYP17, HSD3B2, SRD5A2) prevent normal virilization and can be associated with or mimic testicular dysgenesis. Likewise, defects in androgen action, via the androgen receptor, cause a wide range of undervirilization because of androgen insensitivity. It is useful to distinguish the clinical features of Sertoli cell and Leydig cell dysfunction. If Müllerian regression has occurred, Sertoli cell differentiation and function must have been relatively normal, at least during fetal development. On the other hand, the extent of virilization reflects Leydig cell differentiation, androgen synthesis, and action. In summary, there has been considerable progress in the identification of genetic mutations associated with XY gonadal dysgenesis. Increasingly, these candidates are identified based on phenotypes observed in knockout mice. The important role of gene dosage is a recurring observation for pathways that regulate gonadal development. This feature is dramatically illustrated by mutations in SF-1, which cause a spectrum of phenotypes associated with graded loss of SF-1 function. It is likely that these phenotypes are also influenced by genetic background or modifier genes. This concept can be explored further by identifying additional patients with SF-1 mutations and by examining the effects of Sf-1 mutations in mice of different genetic backgrounds. In practical terms, these recent reports indicate that mutations in SF-1 should be considered in patients with XY gonadal dysgenesis, whether or not there is evidence of adrenal insufficiency (14, 15). This work was supported by National Institutes of Health Grants HD044801 and HD043425. Dosage-sensitive sex reversal-adrenal hypoplasia congenita critical region on the X chromosome,gene 1; steroidogenic factor-1; steroidogenic acute regulatory protein; ventral medial hypothalamus. | F21: 2004.0 | G21: 2004-12-01 | H21: https://doi.org/10.1210/jc.2004-2047 | I21: VALID_TARGET_REFERENCE | J21: HIGH | K21: DIRECT_TARGET_REFERENCE | L21: 著者名ターゲット：Of Mice and Men（Steinbeck）への言及 | M21: OABASEV1_8a27c7bfc7329386 | N21: W000011932 | O21: W1975207593
A22: 67 | B22: The house of mirth | C22: Edith Wharton | D22: A Son at the Front; American Writers and World War I | E22: Wharton scholars will warmly welcome this attractive new edition of Wharton’s war novel in the centenary year of its original publication. Oxford World’s Classics has been producing excellent and affordable editions of novels with informative notes and introductory essays for over one hundred years. However, this is the first time since 2015 that there has been a new addition to their offerings of Wharton’s novels. It is, therefore, of some considerable import that A Son at the Front has been added to The House of Mirth, Ethan Frome, The Custom of the Country, The Age of Innocence, and Summer. In contrast to these other well-known novels, A Son at the Front has not received anywhere near the same attention and acclaim. It was only in 2015, during the centenary commemorations of the First World War, that the Library of America added it to its Wharton portfolio, with notes by Hermione Lee, in a volume containing four of Wharton’s novels published in the 1920s.Julie Olin-Ammentorp has long championed Wharton’s war fiction and her 2004 publication, Edith Wharton’s Writings from the Great War, made a significant contribution to Wharton scholarship. Citations alone testify to its authoritative status. A Son at the Front was for many decades overlooked by literary scholars with the tenacious canonization of texts that subscribed to what Samuel Hynes characterized as the “Myth of War” approach. The broadening of the canon of war writing has gone hand-in-hand with attempts to widen perspectives and to recognize the diversity of experiences and circumstances. In addition, there have been concerted efforts by the European Union and other countries to support Ukrainian culture and its artists. What this tells us is that Wharton’s novel transcends its immediate context and speaks to prominent elements in the representation of war and its impact on life. It contributes to discussions about how to represent conflict, polarization, and propaganda. As such, Wharton’s novel should not only be seen in the context of World War I writings but also in the general context of the war novel.The annotations to this edition of A Son at the Front are more fulsome than the Library of America edition. Inevitably publishers must consider word count, but there is another issue here that is worth raising. Some annotations lend themselves more easily to a so-called factual accounting. Some of those annotations are particularly pertinent with regard to the increasingly distant nature of the novel’s setting and the current time of the reader. However, Wharton’s allusions to a work of art or literature, at the very least, can never be taken at face value. She routinely played with her broad swath of allusions to western cultural traditions and these stretch right across her entire oeuvre. Much of this has to do with her sense of continuity and tradition, and with locating her work within a far larger context. She straddled the need to sell books and her aspiration to be a serious writer of fiction whose work would stand the test of time. The contemporary reviews of A Son at the Front demonstrate only too clearly how reviewers were caught up in the moment and failed to appreciate the mind at work in searching for a way to represent wartime experiences. Readers should therefore not stop at an annotation that provides them with sources and information. Take, for example, how Wharton slips in a reference to Milton’s poem, “Lycidas,” with the phrase “the tangles of Neara’s hair” or her comparison of the coils of a telephone to the serpents coiled around Laocoön. There is so much to be gained from following these up and realizing the intricate playfulness of Wharton’s allusions and how this can influence the interpretation of her novels. Some of her ironic tone can be entirely missed without an appreciation of what she alludes to and how she does so.Olin-Ammentorp’s introductory essay provides a comprehensive survey of the writing and reviews of A Son at the Front, as well as its place in Wharton’s overall oeuvre and in World War I novels. The section on “Seeing Paris” draws attention to how the war is refracted through the eyes of an American expatriate and portrait artist, John Campton. As Olin-Ammentorp points out, he is a difficult protagonist for readers to identify with. This is a gamble on Wharton’s part, given what she wrote in “The Vice of Reading” about the proclivities of the “mechanical reader,” but it also negates any sentimentality. Wharton’s choice, therefore, of this protagonist as her “reflecting mind” enabled her to provide a satirical depiction of the superficiality of some American expatriates’ war efforts. While her representation fits in with her earlier critiques of society figures and their motivations for their display of wealth and philanthropy, there was little in this novel to offer them solace regarding the role of individuals in the “strange war-world of the rear,” let alone the US government prior to the declaration of war. On the other hand, it offered an opportunity for introspection about international outreach and the role of the United States in global affairs, having been published at a time when isolationist rhetoric began to crescendo.There is a further aspect to consider with regard to how Campton sees Paris in wartime. This has to do with Walt Whitman’s descriptions of Washington, DC, at the time of the Civil War. We are alerted to the connection between these and what Wharton portrays in her novel with the prominent positioning of the epigraph, drawn from Whitman’s Specimen Days. There are numerous allusions to Whitman in Wharton’s work and it is worth going beyond the obvious connection in this instance—namely, the way in which Wharton picks up on Whitman’s observations of combatants and the way in which “they are different from the rest . . . ‘something odd about them’” and their tendency to “go off and meditate and muse in solitude” (48). Consider, for example, how Whitman describes Washington, DC, in the moonlight or gaslight and Campton’s “painter’s vision” of the illuminations in the Place de la Concorde and how the light lies on the city in “wide silvery washes” (130). Is there not a possibility that Wharton is prompting the reader to compare Whitman and Campton and their response to the devasting wars in their lifetime? On one hand, there is the two artists’ similar response to light and shape and forms, and on the other, there is a stark contrast between Whitman and Campton. The poet fully embraced the need to visit wounded and dying soldiers in various army hospitals, whereas Campton recoils from hospital visits unless they are to see his son. The contrast underscores Campton’s misanthropic and selfish disposition. If, as Campton insists at the beginning, this is not his son’s war to fight, then it is not America’s war to fight. But Campton undergoes a transformation and stands in for the change in position that Woodrow Wilson’s administration undertook to shift from neutrality to engagement. This pivot was crucial to the increase in the Allies’ military advantage and to the fractious debate within the United States thereafter about the nation’s global role. As such, this makes Wharton’s novel of particular interest to both the history and the ongoing debate of US involvement overseas.There are many reasons to take a new look at Wharton’s novel and to reappraise it. Julie Olin-Ammentorp’s work and her achievement in getting Oxford University Press to publish a scholarly edition of Wharton’s 1923 novel should inspire new efforts. David A. Rennie’s American Writers and World War I provides an overview of a select number of authors who published fiction featuring the Great War. He devotes a chapter to Wharton, to Ellen La Motte together with Mary Borden, to Thomas Boyd, to F. Scott Fitzgerald, to Laurence Stallings, and to Ernest Hemingway. This selection, Rennie argues, is “representative of the diverse influences of World War I on American authors,” who also dealt with the war in several other genres that have garnered less critical attention. He provides a good amount of context for each author and compares them in terms of their relationship to the war, of their writing careers, and of their experience of the publishing industry. Unlike other recent volumes covering a variety of American authors who produced war fiction in the early twentieth century, Rennie probes well beyond the immediate time of the writing and publication of war novels with which the authors are most associated. This provides an opportunity to see their war-related fiction in terms of their overall oeuvre and, more pointedly, to examine how their perspectives on the war may have evolved from 1918 onwards. Wharton scholars will find of particular interest the juxtaposition of Wharton with these other authors, including those long regarded as part of the Lost Generation, and how this enables readers to contextualize her complex and sometimes contradictory responses to the war. Rennie rigorously resists any simplistic and static categorization of individual authors’ reactions, hence the title of his introductory chapter: “The Hell with All the Dirty, Easy Labels”, a quote from F. Scott Fitzgerald. Drawing upon the work of scholars such as Hazel Hutchison and Steven Trout, Rennie draws attention to the struggles that novelists had with making sense of the war, the sacrifice of millions of lives, and the destruction of the built environment and countryside. This volume is firmly located among the work of those who have sought to broaden the field beyond the canonical texts that were predominant in the literary curriculum and anthologies up until thirty or so years ago.Much of Rennie’s coverage is dependent on existing scholarship on individual authors and does not necessarily cover new ground. Wharton scholars, therefore, will not find much in the chapter on Wharton that has not already been covered by Alan Price and Julie Olin-Ammentorp. Rennie’s coverage does not go into great depth and the analysis of Wharton’s war writings is brief. To be fair, the focus is on contexts rather than texts. He emphasizes her Francophilia to the exclusion of her wider knowledge and use of the western literary tradition, particularly with regard to the literary representation of war. Curiously, he omits her use of Whitman in her epigraph for the novel, while pointing to Borden taking inspiration from Whitman’s “A Song of Myself.” The Book of the Homeless is given a section, but there is no analysis of its content or links to her work with refugees or the depiction of “murdered houses” in Fighting France. In Morocco is absent and there is a missed opportunity here to draw a comparison with La Motte. With regard to the latter, Rennie provides a valuable insight into the relationship of the text she wrote during the war following a year’s tour of Southeast Asia criticizing European colonialism with her Backwash of the War and its questioning of the extolling of fighting for liberty, justice, and civilization.As an introduction to American writers and the First World War, Rennie’s book provides a useful overview of seven authors with different experiences of the war and at different stages in their careers, united by their multifaceted and evolving responses to the conflagration. It will enable readers to have a broader appreciation of that part of the American literary community which was, like Wharton, intensely engaged with the war and its impact, and, more importantly, it will encourage readers to make further comparisons. | F22: 2023.0 | G22: 2023-05-01 | H22: https://doi.org/10.5325/editwharrevi.39.1.0078 | I22: VALID_TARGET_REFERENCE | J22: HIGH | K22: DIRECT_TARGET_REFERENCE | L22: OUP既刊リスト中での簡潔な言及 | M22: OABASEV1_2c9d8b89650a9b04 | N22: W000031971 | O22: W4389080899
A23: 68 | B23: Lamb | C23: Charles Lamb | D23: Judith– a seduction | E23: In this second, fully revised edition of his acclaimed study of Barker's work, Charles Lamb sets out to make emotional sense of the characters and their interactions. This is a detailed exploration of the 'scene of seduction' - the challenge, the secret, the abject and the catastrophic, processes which dominate Barker's work. For Lamb, the power of Barker's plays is to be found in the exposure to the irrational and its promotion of a state of unknowing. This revised edition includes: * a new interview with Barker;* a revised introduction, * an updated bibliography * a full production chronology. For students of Barker and for actors and directors working with this unique material, Lamb's book is a vital and illuminating text. | F23: 2010.0 | G23: 2010-02-16 | H23: https://doi.org/10.4324/9780203324288_chapter_4 | I23: INVALID_TARGET_REFERENCE | J23: HIGH | K23: AUTHOR_COLLISION_DIFFERENT_PERSON | L23: Howard Barker研究者のCharles Lamb（現代の演劇研究者）。同名異人 | M23: OABASEV1_60293e5b089b650c | N23: W000020329 | O23: W2486734876
A24: 69 | B24: Short stories | C24: D. H. Lawrence | D24: СОДЕРЖАНИЕ НА АНГЛИЙСКОМ ЯЗЫКЕ | E24: PERM UNIVERSITY HERALD ––––––––––––––––––––––––––––––––––––––––––––––––––––––––––––– 2015 RUSSIAN AND FOREIGN PHILOLOGY Issue 2(30) CONTENTS LANGUAGE, CULTURE, SOCIETY Svetlana S. Shlyakhova SOUND-GRAPHEME-COLOR SYNAESTHESIA OF CONSONANTS IN THE KOMI-PERMYAK LANGUAGE. Article 2. Discussion of the experiment…………………...……5 Irina B. Kachinskaya KINSHIP TERMS IN THE MYTHOLOGICAL DIMENSION (a case study of Arkhangelsk dialects)……………………………………………………………..................16 Svetlana A. Ganicheva SEMANTIC FEATURES OF RUSSIAN DIALECT VERBS DENOTING ANIMAL AND BIRD VOICES (BASED ON «LEXICAL ATLAS OF RUSSIAN FOLK DIALECTS»)…………………………..……..…27 Natalia G. Kutrueva ON THE PERCEPTION OF SOME RUSSIAN HESITATION FILLER WORDS BY SPEAKERS OF OTHER LANGUAGES……………………………………….…...34 Elena A. Brylina, Olga G. Sidorova THE FIRST RUSSIAN GRAMMAR BOOKS OF THE ENGLISH LANGUAGE: CONTENT, PRESENTATION OF GRAMMAR MATERIAL, METHODS………………………………………………………………….44 Svetlana L. Mishlanova, Tatyana S. Katlishina CONSTRUCTION OF THE MEANING OF THE WORD “STRUGGLE” IN ENGLISH……………………………………………………………...53 Marina O. Kunshchikova MODELS OF WORDPLAY FORMATION IN THE CONTEXT OF CLASSROOM BILINGUALISM……………………………………………..62 Ning Wan ADVERTISING TEXT IN TERMS OF CULTURE AND INTERCULTURAL COMMUNICATION………………………………………………...………….69 Evgeniya P. Bogatikova METAPHORS IN THE CONTEXT OF ONLINE HEALTH COMMUNICATION………………………………………………………….……77 Valery A. Mishlanov, Vladimir A. Salimovsky MODERN CLERICAL AND RELIGIOUS DISCOURSE IN TERMS OF FORENSIC LINGUISTICS ISSUES……………….......84 LITERATURE IN THE CULTURAL CONTEXT Nataliya A. Petrova THE ART OF CUTTING OUT AND SEWING (NOTES ON THE SUBJECT)…….97 Marina V. Tsvetkova IMAGES OF SQUIRES-ANGLOMANIACS th IN RUSSIAN LITERATURE OF THE XIX CENTURY…………………………………………………106 Boris M. Proskurnin THE SUBVERSION OF LINEAR TIME IN ‘SONS AND LOVERS’ BY D.H. LAWRENCE…………………………………….………………….112 Tatyana N. Fominykh THE IMAGERY OF THE LYRIC NOVELLA «THE WAY OF THE PIGEON» BY V. I. STRAZHEV…………………………………………………...120 Svetlana V. Burdina, Olga A. Mokrushina THE TOPOS OF POST-SOVIET SCHOOL IN RUSSIAN SHORT STORIES OF THE TURN OF THE XXI CENTURY………………….................129 4 | F24: 1994.0 | G24: 1994-12-01 | I24: INVALID_TARGET_REFERENCE | J24: MEDIUM | K24: WRONG_WORK_SAME_AUTHOR | L24: 目次中に "Sons and Lovers by D.H. Lawrence"（長編）論文あり。ターゲット「Short stories」は別の作品群 | M24: OABASEV1_5309e15aa02802b9 | N24: W000030610 | O24: W4290239718
A25: 70 | B25: Marie de France | C25: Marie de France | D25: The Lais of Marie de France: Text and Context | F25: 1989.0 | G25: 1989-09-01 | H25: https://doi.org/10.2307/3200189 | I25: VALID_TARGET_REFERENCE | J25: HIGH | K25: DIRECT_TARGET_REFERENCE | M25: OABASEV1_c8768eec321143c3 | N25: W000000860 | O25: W1998164323
A26: 71 | B26: Mildred Pierce | C26: James M. Cain | D26: James M. Cain | E26: James M. Cain wrote some of the grittiest novels in American literature, including such classics as The Postman Always Rings Twice, Double Indemnity, and Mildred Pierce. James M. Cain: Hard-Boiled Mythmaker is a critical overview of the author's life, work, and legacy. An updated and expanded edition of two of David Madden's scholarly works on Cain, this new book improves upon the previous works by collecting the most essential writing on Cain by Madden into one volume. In addition to melding existing material, this work contains updated and new material, including fresh commentaries on later books, such as Rainbow's End, Cloud Nine, and The Enchanted Isle, as well as later film adaptations, including Butterfly. It also responds to 40 years' worth of criticism on Cain and reevaluates his influence. Providing an overview of all of Cain's fiction, including an analysis of the major themes of his entire literary career, the book also describes Cain's impact on and importance in 20th-century culture, film in particular. In addition to a biographical summary and thematic outline of Cain's nearly 50-year career, Madden and Mecholsky examine how Cain's works explore the nightmare consequences of the persistent American dream. Finally, Madden and Mecholsky consider Cain's technical innovations of the novel and survey the major film adaptations of Cain's novels. With its significant in-depth analysis and a foreword by Edgar-award winning author Max Allan Collins, this volume will be of interest to Cain scholars as well as anyone interested in 20th century American literature and film. | F26: 2011.0 | G26: 2011-01-01 | H26: https://doi.org/10.5040/9798881819002 | I26: VALID_TARGET_REFERENCE | J26: HIGH | K26: DIRECT_TARGET_REFERENCE | M26: OABASEV1_5df7caab72622112 | N26: W000016816 | O26: W4410667208
A27: 72 | B27: Stories | C27: Erskine Caldwell | D27: The Complete Stories of Erskine Caldwell | F27: 1980.0 | G27: 1980-06-01 | I27: VALID_TARGET_REFERENCE | J27: HIGH | K27: VALID_TITLE_VARIANT | L27: Complete Stories＝Stories | M27: OABASEV1_d38b9725a89fe475 | N27: W000001554 | O27: W1582846553
A28: 73 | B28: Edgar Allan Poe | C28: Edgar Allan Poe | D28: Poe in the Marketplace: Making Sense of Reprinting Jonathan H. Hartmann. The Marketing of Edgar Allan Poe. In Studies in American Popular History and Culture, ed. Jerome Nadelhaft | F28: 2011.0 | G28: 2011-10-01 | H28: https://doi.org/10.1111/j.1754-6095.2011.00042.x | I28: VALID_TARGET_REFERENCE | J28: HIGH | K28: DIRECT_TARGET_REFERENCE | M28: OABASEV1_c5b045768f6aa4a8 | N28: W000018534 | O28: W1531429259
A29: 74 | B29: The Waves | C29: Virginia Woolf | D29: The Mythological Element in Virginia Woolf's The Waves: Bernard's Vision | E29: Readers A n d Critics of Virginia Woolf seldom, if ever, discuss the religious dimension in her writings.W oolfs atheism (or "agnosti cism") perhaps prevents her readers from perceiving the religious attitude in her work.While it is true that Woolf admits her distrust of organized religious answers, it is also true that she expresses a deeply mythic or religious (I use the words interchangeably) view of life in her art.Of all Woolfs novels, The Waves comes closest to expressing a mythic vision of life.H er interest in the androgynous artist; her attention to "moments of being"; her passion for finding a true self in the flux of time; her use of symbols to express a complex, spiritual vision: these elements in her writing combine to create a mythic vision.The characters, though they are historically bound, achieve symbolic universality in their soliloquies.Bernard, one of the seven characters in the book, is Woolfs expression of the artist in quest of a total vision of life.We see Bernard, the "phrasemaker," in the process of coming to terms with his Self within the flux of time.Significantly, he utters the first and last words of the novel.In the final soliloquy, he expresses the summary statement."Now to sum up . . .Now to explain to you the meaning of my life."1Thus he begins his last utterance.He speaks "freely" of the "illusion . . .that something adheres for a moment, has roundness, weight, depth, is complete.This, for the moment, seems to be my life.If it were possible, I would hand it to you entire" (p.238).Earlier he says: "We are the creators.We have made something that will join the innumerable congrega tions of past time" (p.146).Bernard represents not so much a participant in this or that morsel of history, but spiritual entity, in the | F29: 1986.0 | G29: 1986-01-01 | H29: https://doi.org/10.17077/0743-2747.1195 | I29: VALID_TARGET_REFERENCE | J29: HIGH | K29: DIRECT_TARGET_REFERENCE | M29: OABASEV1_cf3efcd6d2d77ddd | N29: W000018002 | O29: W306585970
A30: 75 | B30: Poems | C30: Robert Louis Stevenson | D30: Quick and Bright but Somewhat Desultory Scholar | E30: From Robert Louis Stevenson: A Life Study in Criticism (1901) 18–23. Henry Bellyse Baildon (1849–1907) met Louis at Robert Thompson’s day school in Frederick Street, Edinburgh, in 1864 and they collaborated in the school magazine until Baildon left for the University in the autumn of 1865, where their friendship later resumed. He remained one of those friends to whom Louis in Samoa could indulge his nostalgic longings for Scotland. Baildon was the author of Rosamund, a Tragic Drama (1875) and several books of poems. He contributed the Stevenson entry to Homes and Haunts of Famous Authors (1906). In Temple Bar , 104 (March 1895) 325–33, he paid tribute to Stevenson as the enemy of moral pedantry and the most genuinely modest of men, revolted by the grim severity of Calvinism, yet with ‘his own rather exacting standards for human behaviour’ (331). These keywords were added by machine and not by the authors. This process is experimental and the keywords may be updated as the learning algorithm improves. | F30: 1996.0 | G30: 1996-01-01 | H30: https://doi.org/10.1007/978-1-349-24355-6_5 | I30: INVALID_TARGET_REFERENCE | J30: MEDIUM | K30: TITLE_AUTHOR_UNLINKED_COOCCURRENCE | L30: Stevenson伝記的抜粋。「books of poems」はBaildonの著作で、Stevensonの Poems への参照はない | M30: OABASEV1_705544e41a36d8fb | N30: W000005423 | O30: W2401618994

Sheet Audit 04
A1: OpenAlex R2+A1 Blind Human Audit — R2A1A04
A2: 判定対象：OpenAlex record が target literary work を本当に参照しているか。LLM判定・sampling stratum・risk featureは非表示です。Web検索はしません。
A4: 入力欄 → | I4: Judgment | J4: Confidence | K4: Reason | L4: Reviewer note
A5: Review # | B5: Target title | C5: Target author | D5: OpenAlex record title | E5: OpenAlex abstract | F5: Year | G5: Publication date | H5: DOI | I5: Judgment | J5: Confidence | K5: Reason | L5: Reviewer note | M5: Candidate ID | N5: Project Work ID | O5: OpenAlex Work ID
A6: 76 | B6: Heart of darkness | C6: Joseph Conrad | D6: Feminine images and shadow projection of deracinement in Heart of Darkness | E6: In Joseph Conrad's works of depicting sea journey and European colonization,female characters are comparatively fewer and weaker.Yet in his masterpiece Heart of Darkness,there are not only five female characters but also abundant feminine images,from darkness and heart in the title to river,Africa,primitive,land,shadow,etc.which prevail through the whole novel. Do these feminine images have something to do with the sense of guilt of his so-called betrayal to his motherland or are they the shadow projection of his deracinement? The present paper sets to get these feminine images connected with Conrad's miserable childhood,his betrayal to his motherland,his sense of guilt and his deracinement,therefore to interpret how Conrad made use of these feminine images to memorize his childhood and how he gained Katharsis and expiation by means of shadow projection. | F6: 2007.0 | G6: 2007-01-01 | I6: VALID_TARGET_REFERENCE | J6: HIGH | K6: DIRECT_TARGET_REFERENCE | M6: OABASEV1_10e8fd8081d84a16 | N6: W000030652 | O6: W2385656498
A7: 77 | B7: McTeague | C7: Frank Norris | D7: Combating Injustice: The Naturalism of Frank Norris, Jack London, and John Steinbeck | E7: Jon Falsarella Dawson begins Combating Injustice: The Naturalism of Frank Norris, Jack London, and John Steinbeck by proposing a reinterpretation of the familiar literary movement, naturalism, through a distinct theoretical lens, social critique. He is particularly interested in investigating financial and economic questions, a line of inquiry that has not been as frequently applied to naturalist texts. Traditionally, the movement has been linked to its origins in nineteenth-century biological and sociological discourses, particularly the Lamarckian and Spenserian strands that occupied the social imaginary. Such traditional criticism often connected these discourses with recurrent themes of determinism. Dawson pivots within this critical trend, offering an alternative approach to similar thematic concerns. He writes that “economic determinism is central to social criticism in American naturalism” (5). For Dawson, themes of determinism can be closely connected to causative economic forces. Thus, the restriction of the individual’s agency is less biological (as in traditional readings) than economic and social. Dawson proposes that naturalist writers use this economic determinism in service of their broader social critique.Combating Injustice comprises eight chapters. In addition to the book’s introduction and conclusion, each of selected important writers receive two chapters dedicated to their work. Dawson focuses on Norris’s McTeague and The Octopus; London’s Martin Eden, The Iron Heel, and two short stories; and Steinbeck’s In Dubious Battle and The Grapes of Wrath. Each chapter maintains, for the most part, a consistent pattern. Dawson begins by providing historical context for each work, drawing attention to the prevailing political and economic structures. His selection of historical material is acute and directly serves his literary analysis throughout. He then moves to an extended close reading, tracing the texts’ engagement with and transformation of the historical moment. His theoretical approach is brought alongside the text, rather than being callously imposed upon it. Dawson draws numerous compelling examples and repeatedly clarifies how economic forces manifest in these texts. The style of his prose is both measured and clear, articulating nuanced interpretations in an accessible way. In many regards, Dawson’s prose is exemplary, avoiding the opaque jargon that can sometimes detract from literary arguments.His chapters on Norris are especially strong. Dawson emphasizes the cultural weight that issues of monopoly, speculation, and financial innovation carried during Norris’s career and in the fictional world of his novels. In his discussion of both McTeague and The Octopus, Dawson traces how national economic structures circumscribe characters’ actions. Furthermore, he highlights themes of industrial extraction and the “tragedies that emerge from privileging financial gain over the common good” (68). In his treatment of Norris, Dawson emphasizes the power and scope of economic systems. This macro-level concern responds to the ambitious scope of Norris’s wheat trilogy. Norris was interested in the broad mechanics of economy and planned to trace the movements of a single commodity (wheat) from Californian farmers (The Octopus), to Chicagoan distributors (The Pit), and then to European consumers (The Wolf [unwritten]). Dawson’s critique ambitiously engages the mechanics of such large systems.The chapters on London are equally insightful. Dawson shifts from Norris’s emphasis on systems to London’s interest in the cultural repercussions of such structures. Given London’s ardent socialist bent, Dawson’s analysis finds ample instances of political and economic representation. Furthermore, he follows London in paying particular attention to the working conditions that plagued the lower class. Dawson outlines the interpersonal deterioration and individual alienation manifested in London’s proverbial “work-beast” and Martin Eden’s class ascension. He articulates the dehumanizing effects of industrial efficiency. The brutal commitment to mere production transformed a character like Johnny (“The Apostate”) into an “abnormal creature that violates the patterns of the world” (78).Dawson’s chapters on Steinbeck offer excellent introductions to the historical context that deeply informed In Dubious Battle and The Grapes of Wrath. Furthermore, Dawson does a nice job situating Steinbeck’s political perspectives alongside his complex concerns as a writer. For example, in his discussion of In Dubious Battle, Dawson engages Steinbeck’s commentary on the novel: “I have used a small strike in an orchard valley as the symbol of man’s eternal, bitter warfare with himself. . . . I’m not interested in strike as a means of raising wages, and I’m not interested in ranting about justice” (145). On the face of it, this insight weakens an economic and social interpretation of the text. However, Dawson provides a crucial gloss: “While Steinbeck deemphasizes the concrete aims of labor struggles, they do provide the context for the representation of issues fundamental to the human enterprise, an approach that expands the project from a mere muckraking book to an exploration of the forces that animate behavior” (145). Dawson aptly describes how the symbolic approach does not negate the importance of the context. The material conditions of the labor struggle mediate “issues fundamental to the human enterprise.” While In Dubious Battle is not a proletarian novel (the strikers are not idealized), Dawson argues that Steinbeck was not politically neutral. Steinbeck often occupied a liminal space between political poles; on the right, he was too sympathetic to communism; on the left, he was not sympathetic enough. While acknowledging that the text resists the didactic melodrama of a muckraking novel, Dawson argues that Steinbeck clearly emphasizes the need to alter the economic conditions that were responsible for the conflict. Dawson writes, “In Dubious Battle suggests the clash must inevitably take place despite the vast obstacles against the victory of labor in order to alter socioeconomic conditions” (161).In his reading of In Dubious Battle, Dawson also extends his argument regarding economic determinism. He writes that Steinbeck’s animal imagery “reiterates the causative function of the landowners, signifying that the laborers have been reduced to their present conditions by the practices of the powerful” (155). While Dawson acknowledges Steinbeck’s interest in the phalanx, he ultimately places far more emphasis on the causative forces of the owners. Therefore, the strikers’ violent actions are more determined by particular social pressures than the universal phalanx phenomenon. The degree to which Dawson interprets economic determinism in In Dubious Battle may strike some Steinbeck scholars as overstated.In his chapter on The Grapes of Wrath, Dawson continues to extend previous interpretations. He contends that “socioeconomic” forces explain the Joads’ exodus and delineate their actions throughout the novel (162). The deterministic reading is particularly bold throughout this chapter: “representations of capital comprise the primary deterministic agents in The Grapes of Wrath” (167). While such a claim can be closely substantiated by examples from Norris and London (and, to a lesser degree, In Dubious Battle), this economic interpretation may strike some readers as more tenuous in regard to Grapes. The ecological disaster, which Dawson briefly mentions, is explained as an outworking of “economic motives” (169). Considering the cultural, religious, environmental, and political influences that created the Dust Bowl, the attribution of the event to a causative economic base seems reductive. In other places, the theoretical framework feels likewise strained. At one point, Dawson describes Ma Joad’s compassion as “indicating that the poor have an obligation to their class” (184). This “class” language subtly undermines the broader universal compassion that Steinbeck deeply engrains in the novel.Despite these quibbles, Dawson’s broader framework is still a helpful hermeneutic for Grapes, specifically his attention to alienation. In resonance with London’s emphasis on dehumanization, Steinbeck emphasizes the negative effects that accompany instrumental practices and industrial efficiency. Dawson quotes, for instance, this famous descriptive phrase from Grapes: “the machine man, driving a dead tractor on land he does not know or love” (qtd. 168). When the world is approached as a mere accumulation of resources, humanity’s relationship with the natural world becomes sterile. Throughout the book, Dawson repeatedly connects this alienation to broader economic structures. In this sense, his interpretation provides a language to identify such threads of personal and social regression.Dawson concludes Combating Injustice by reiterating that Norris, London, and Steinbeck engage ideas of economic determinism in order to illuminate social issues and ameliorate material conditions (186). The later part of his argument represents a substantial shift in understanding the naturalist mode. Dawson diverts attention from the failings of the individual, writhing under natural and obscure forces, toward the importance of collective action and the potential for improvement. In this way, Dawson provides an optimistic avenue for approaching naturalism; while humanity is restricted by external forces, these forces are largely manufactured and impermanent. Dawson draws our attention to the possibility of reform and revolution, which is manifested across these writers’ work. Combating Injustice is an excellent thematic survey of its selected writers and provides a rich historical overview of American economic tensions, tensions which have remained relevant and important in modern discourse. | F7: 2023.0 | G7: 2023-12-01 | H7: https://doi.org/10.5325/steinbeckreview.20.2.0293 | I7: VALID_TARGET_REFERENCE | J7: HIGH | K7: DIRECT_TARGET_REFERENCE | M7: OABASEV1_262c5d119ec3bebb | N7: W000008097 | O7: W4390414700
A8: 78 | B8: Galen | C8: Galen | D8: Kalp Anatomisinin Tarihsel Serüveni | E8: ÖzetTıp, insanlıkla birlikte varlığını sürdüren ve insan hayatının vazgeçilmez bir unsurudur. Tarih boyunca kalbin vücutta önemli bir fonksiyonu olduğuna inanılmıştır. Amacımız, tarih boyunca vücutta önemli bir fonksiyonu olduğu inanılan kalbin tarihsel gelişimini, anatomik gelişmeler açıdan değerlendirmektir. Eski uygarlıklarda damarlarda sadece kan değil aynı zamanda havanın olduğu kabul ediliyordu. Bu döneme ait eserlerde kalp atışlarından da bahsedilmektedir. Antik Yunan döneminde arterler ile venlerin farklı yapılar olduğu tespit edilmiştir. İskenderiye Tıp Okulunda kalbin bir pompa gibi çalıştığından, trikuspid kapak ve fonksiyonlarından bahsedilmiştir. Roma dönemi bilginlerinden Galen yaptığı çalışmalar sonucunda kanın ventriküller arası bölmeden geçiş yaptığını ileri sürmüştür. Bu görüş “otoriteye koşulsuz bağlılık” düşüncesi nedeniyle, 17. yy’a kadar varlığını devam ettirmiştir. İbn Sînâ, Galen’in halefi olarak kabul edilmiştir. İbn ün-Nefis yaptığı araştırmalar sonucunda Galen ve İbn Sina’nın aksine ventriküller arası bölmeden geçişin olmadığını belirtir. Ayrıca İbn ün-Nefis 13. yy da küçük pulmoner dolaşımı keşfetmiştir. 1500’lü yıllardan itibaren kan dolaşım sisteminden, koroner damarlardan, kalp kapakçıklarından ve kılcal damarlardan bahsedilmiştir. Tarihsel süreçte kalbin anatomik yapısı ve çalışma sisteminin tespiti ilk çalışma konuları olarak karşımıza çıkmaktadır. Daha sonra ki süreç kan gruplarının tespitinden kalp naklinin gerçekleştirilmesine kadar ki aşamaları içermektedir.AbstractMedicine has existed with humanity and it is an indispensable element of human life. Throughout history, the heart has been believed to possess an important function in the body. Our aim historical development of the heart is evaluate in terms of the anatomical developments. In the ancient civilizations, it was demonstrated that there were both blood and the air in the vessels in the body. Moreover, the heart beats have been mentioned. In ancient Greece, it was identified that the arteries and veins had different functions. In Alexandria Medical School were discussed the tricuspid valve and its functions. According to Galen some blood from the right ventricle to the left ventricle transfers via pores found in the septum. This theory domiated Western medicine until 17th centruy due to “strict obedience to authority”. Avicenna, as the successor of Galen has been recognized. Ibn al-Nafis unlike Galen and Avicenna clearly described that blood came from the right heart to the lungs and mixed there with air and then returned to the left heart. Ibn al-Nafis discovery of pulmonary circulation in 13th centruy. In the historical process, the first study subject were about anatomical and physiological structures of the heart. Then the process have included all stages form determination of blood groups to a heart transplant. | F8: 2014.0 | G8: 2014-01-01 | I8: VALID_TARGET_REFERENCE | J8: MEDIUM | K8: VALID_CONTEXTUAL_REFERENCE | L8: 著者名ターゲット：心臓解剖史でGalenの学説に言及 | M8: OABASEV1_7d3239ae26c355f7 | N8: W000031472 | O8: W2266493076
A9: 79 | B9: The Yearling | C9: Marjorie Kinnan Rawlings | D9: Preserving Southern Culture: Marjorie Kinnan Rawlings’s The Yearling | F9: 2017.0 | G9: 2017-09-20 | I9: VALID_TARGET_REFERENCE | J9: HIGH | K9: DIRECT_TARGET_REFERENCE | M9: OABASEV1_86edba5fdb224b89 | N9: W000000940 | O9: W7014557848
A10: 80 | B10: Herland | C10: Charlotte Perkins Gilman | D10: Herland (1915): Charlotte Perkins Gilman¿s Critiques of Patriarchal Society through Utopia | F10: 2020.0 | G10: 2020-01-01 | I10: VALID_TARGET_REFERENCE | J10: HIGH | K10: DIRECT_TARGET_REFERENCE | M10: OABASEV1_549417355f81874d | N10: W000014039 | O10: W7066006703
A11: 81 | B11: Marie de France | C11: Marie de France | D11: The fusion of magic and realism in two lays of Marie de France | F11: 1975.0 | G11: 1975-07-01 | H11: https://doi.org/10.1007/bf01514003 | I11: VALID_TARGET_REFERENCE | J11: HIGH | K11: DIRECT_TARGET_REFERENCE | M11: OABASEV1_f144ede547729329 | N11: W000000860 | O11: W2042527393
A12: 82 | B12: Henry James | C12: Henry James | D12: MRS HUMPHRY WARD, VERNON LEE, AND HENRY JAMES | E12: PETER COLLISTER; MRS HUMPHRY WARD, VERNON LEE, AND HENRY JAMES, The Review of English Studies, Volume XXXI, Issue 123, 1 January 1980, Pages 315–321, https://do | F12: 1980.0 | G12: 1980-01-01 | H12: https://doi.org/10.1093/res/xxxi.123.315 | I12: VALID_TARGET_REFERENCE | J12: HIGH | K12: DIRECT_TARGET_REFERENCE | M12: OABASEV1_047e5cb3d248688a | N12: W000014024 | O12: W2070119163
A13: 83 | B13: Ulysses | C13: James Joyce | D13: "Space: what you damn well have to see": Psychogeography in James Joyce's Ulysses | F13: 2018.0 | G13: 2018-01-01 | H13: https://doi.org/10.15781/t2rn30r89 | I13: VALID_TARGET_REFERENCE | J13: HIGH | K13: DIRECT_TARGET_REFERENCE | M13: OABASEV1_3f1d3632073eff18 | N13: W000016985 | O13: W6962492117
A14: 84 | B14: The Best Short Stories of 1932 | C14: Edward J. O'Brien | D14: The Kane Penn, vol. 1, no. 20 | E14: Volume 1, issue number 20 from The Kane Penn, a semi-monthly newsletter by members of CPS Camp 16 in Kane, Pennsylvania. The issue reports on the following topics: overview of a camp meeting; highlights from a recent track meet; recollecting the passing of Selective Service regulations and the testimonies made on behalf of the conscientious objectors at subsequent hearings; the first regular get-together by the Redbridge Players; quote from General Hershey concerning draft board rejections; reflections on what education to offer Campers; humorous anecdotes; spotlight on ‘The Best Short Stories of 1932’ edited by Edward J. O’Brien; list of new arrivals and transfers; random ‘oddities’ from world news; spotlight on periodicals available to read in the library; the doctrines of the Faith Tabernacle religious group; Camp Kane statistics. Note: under the heading for Faith Tabernacle Doctrines, is an editor’s note which reads: ""This is the third of a series of articles concerning the different religious faiths held by members of this camp."" The issue was addressed to M. B. Rovner, Buffalo Teacher, Editor, in Buffalo, New York. | F14: 1943.0 | G14: 1943-07-11 | I14: VALID_TARGET_REFERENCE | J14: HIGH | K14: DIRECT_TARGET_REFERENCE | M14: OABASEV1_2b849649999ab44b | N14: W000010602 | O14: W7209882607
A15: 85 | B15: Galen | C15: Galen | D15: PRACTICAL DEDUCTIONS FROM URINARY FINDINGS IN DIABETES | E15: Since the days of Aretæus, 150 A. D., the first to use the term diabetes—the Greek word for siphon, the fanciful analogy being invoked by three of the cardinal symptoms of the disease, namely, thirst, emaciation and diuresis—the urine has always been looked on as the chief source for diagnosis in diabetes. Hippocrates, Celsus and Galen, in describing this malady, make continuous reference to the "sweet and honey urine." Glucose was first isolated and demonstrated in the urine in 1770 by Matthew Dobson of Liverpool. With the recent remarkable advance of medicine, particularly with the progress of pathology and physiologic chemistry, the finding of diabetic urine not only makes the diagnosis of the disease, but throws light on the etiology, gives valuable aid to the surgeon and obstetrician in solving their problems when diabetes occurs as a complication, and is the guiding star in diagnosis and treatment. In | F15: 1910.0 | G15: 1910-03-12 | H15: https://doi.org/10.1001/jama.1910.92550370001001g | I15: VALID_TARGET_REFERENCE | J15: MEDIUM | K15: VALID_CONTEXTUAL_REFERENCE | L15: 著者名ターゲット：Galenの糖尿病記述への言及 | M15: OABASEV1_25f0615e889025b7 | N15: W000031472 | O15: W2083005922
A16: 86 | B16: Heart of darkness | C16: Joseph Conrad | D16: Ama Ata Aidoo's Heart of Darkness | E16: This essay reads Aidoo's novel Our Sister Killjoy as a postcolonial revision of Joseph Conrad's Heart of Darkness. While both novels have been accused of being racist texts, this essay argues that the implied existence of Conrad's text is crucial for our understanding of Aidoo's racist representational strategies. The drama of Aidoo's novel lies in approaching and refraining from the horror of the racism of Conrad's Heart of Darkness. | F16: 2004.0 | G16: 2004-01-01 | H16: https://doi.org/10.1353/ral.2004.0015 | I16: VALID_TARGET_REFERENCE | J16: HIGH | K16: DIRECT_TARGET_REFERENCE | M16: OABASEV1_efa21d9d35bac274 | N16: W000030652 | O16: W4253841904
A17: 87 | B17: The vicar of Wakefield | C17: Oliver Goldsmith | D17: Oliver Goldsmith’s The Vicar of Wakefield and Cesare Beccaria’s On Crimes and Punishments | E17: This paper posits the influence of Cesare Beccaria’s Dei delitti e delle pene on the development of characters and episodes in Oliver Goldsmith’s The Vicar of Wakefield using the close analogies between the two texts, particularly the later chapters of the novel, the time lapse between the sale to the publisher and the eventual publication of the novel that allowed for revisions and additions to the text, and the spread of Beccaria’s ideas in England prior to the English translation of his work. | F17: 2019.0 | G17: 2019-05-27 | H17: https://doi.org/10.13128/ds-25446 | I17: VALID_TARGET_REFERENCE | J17: HIGH | K17: DIRECT_TARGET_REFERENCE | M17: OABASEV1_0f86370af9f9066a | N17: W000018882 | O17: W2963224946
A18: 88 | B18: Charles Lamb | C18: Charles Lamb | D18: Coleridgean Contributions | E18: By 1802, Coleridge had begun to suspect what the next thirty years would confirm – that there was a ‘radical Difference’ between Wordsworth’s conception of poetry and his own ( CL STC II. 830). Lyrical Ballads was the outcome of a period of initial excitement when, at the start of a relationship, each man was able to suspend his difference and, for a while, be a version of himself that met the other’s hopes and ideals. As such, it was a typical project for Coleridge, who had an intense need to be part of a literary circle in which friendship gave rise to, and was in turn intensified by, communal writing, reading and publishing. He had been co-writing or co-publishing poems with Southey since 1794; in 1797 his first verse collection included poems by his friends Charles Lloyd and Charles Lamb. Wordsworth, on the other hand, had never published collaboratively before and never would again. In a sense, then, Lyrical Ballads (1798) was a Coleridgean volume, one of many co-authored outlets for a practice of versifying that he shared with friends – a practice that was often self-reflexive: the poems were often about the shared experiences of the friends with whom they were written and/or to whom they were recited. A case in point was ‘This Lime Tree Bower My Prison’, the poem in which Coleridge first invoked William and Dorothy in the conversational voice that he and Wordsworth would develop during the next five years. The poem features Charles Lamb as well as the Wordsworths and was recited to them on the spot where it was composed. It was not, however, published in Lyrical Ballads but in Southey’s Annual Anthology alongside contributions by other members of the circle – including Joseph Cottle, the Bristol bookseller who published both it and Lyrical Ballads . This pattern suggests that Lyrical Ballads was just one of many joint publications by which Coleridge sought to promote the innovatory poetic style of the West Country circle, and in so doing endorse their group language. Other poems went into the columns of The Morning Post , where verse by Southey and by Mary Robinson (a satellite member of the group) also appeared. | F18: 2020.0 | G18: 2020-01-09 | H18: https://doi.org/10.1017/9781108236300.006 | I18: VALID_TARGET_REFERENCE | J18: HIGH | K18: DIRECT_TARGET_REFERENCE | L18: 著者名ターゲット：Coleridge詩集に収録されたLambの詩、Lambが登場する詩への言及 | M18: OABASEV1_c6a705fee33ff22b | N18: W000014829 | O18: W4245878286
A19: 89 | B19: Henry James | C19: Henry James | D19: 0. Introduction: Transatlantic North American Studies | E19: Text and Theory series.It responds to the considerable surge of interest in transatlantic literary and cultural studies that has impacted the discipline of North American Studies for the last twenty years.Like many other approaches that fall within the orbit of what is usually called the 'transnational turn,' transatlantic studies seek to give accounts of literary and cultural developments and phenomena now that 'nation' has become a heavily contested concept, replacing the nation-state with the Atlantic world as a site of cultural production.Transatlantic studies have provided important new perspectives on both North American and English (whereby is meant both British and Irish, unless specified differently) literature, producing a multitude of publications and research projects exploring periods, aesthetic developments, genres, the works and artistic biographies of individual authors as well as literary culture in a broad sense.Adopting a bifocal perspective, scholars have examined the complex processes of intellectual and material exchange defining the Atlantic world ever since the days of its exploration and their effect on literary writing.Rather than dwelling on comparisons or engaging with the notion of 'influence,' transatlantic literary studies seek to understand North American and English literature as irreducibly linked with each other by virtue of historical and cultural ties and pay special attention to the many refractions and mutual interferences that have characterized both traditions.This has led to a revision of literary history, a rethinking of preconceived ideas of the canon and national literature, a new approach to genres and texts and a reconsideration of the Anglo-American literary market and its manifold processes of production, distribution, reception and criticism.This handbook combines articles that present some of the crucial concepts, debates and topics in transatlantic literary studies, thereby reflecting on the added benefit of a distinct transatlantic perspective in contradistinction to other related approaches similarly interested in literature as a transnational phenomenon, such as 'comparative (American) studies,' 'transnationalism' or 'post-colonialism.'For example, contributions contained in this volume examine periods in literary and cultural history when transatlantic relations were particularly dense (such as the colonial period), literary movements (such as modernism or romanticism) and individual authors (e.g., Henry James) with strong transatlantic profiles, as well as genres that | F19: 2016.0 | G19: 2016-05-10 | H19: https://doi.org/10.1515/9783110376739-002 | I19: UNCERTAIN | J19: LOW | K19: INSUFFICIENT_CONTEXT | L19: 表示テキスト（transatlantic studies序論）にHenry Jamesの言及なし | M19: OABASEV1_ba893178e8a4a23f | N19: W000014024 | O19: W2500488739
A20: 90 | B20: Josephus | C20: Flavius Josephus | D20: Der Kaiser Claudius : eine historische Studie | E20: iliiiiÄiiifii Der Kaiser Claudius spielt in der Geschichte keine hervorragende Rolle.Er gilt als geistig minderwertig, unselbständig, feig und grausam, trotzdem eine Menge von Zügen von ihm erzählt wird, die mit dieser Ansicht in offensichtigem Widerspruch stehen.Um sich ein gerechtes Urteil über diesen Mann bilden zu können, muß man festhalten, daß es mit der Wahrheitsliebe der Ge¬ schichtsschreiber der ersten Kaiserzeit nicht weit her ist.1) Steckte doch noch zu viel republikani¬ sches Blut in den Kreisen, die sich der Geschichtsschreibung widmeten, um in der Beurteilung der Kaiser volle Gerechtigkeit walten zu lassen.Dies zwingt uns selbst einem Tacitus gegenüber, ob¬ wohl dieser zweifellos gerecht sein will, zur Vorsicht und berechtigt uns zum Mißtrauen bei Nach¬ richten, die geeignet sind, die Vertreter des Kaisertums in den Augen der Leser herabzusetzen.Schon hat eine gerechtere Beurteilung des Tiberius Platz gegriffen; aber auch Claudius, dessen Bild heute noch allzu sehr verdunkelt erscheint, verdient es, gegen unbegründete Vorwürfe seiner Zeitgenossen in Schutz genommen zu werden.I. Claudius vor seiner Thronbesteigung.Claudius oder mit seinem vollen Namen Tiberius Claudius Drusus Nero Germanicus 2), der jüngste Sohn des Prinzen Drusus und der jüngeren Antonia, wurde am 1. August unter dem Konsulate des Julius Antonius und Fabius Africanus d. i. im Jahre 10 vor.Chr.zu Lugdunum ge¬ boren' 1), wohin seine Mutter ihrem Gemahl von Rom aus gefolgt war.Nach dem frühen Tode seines Vaters, 9 vor Chr., siedelte Antonia mit ihm und seinen älteren Geschwistern Germanicus und Livilla von dort wieder in die Hauptstadt über, wo sie sich, zu dauerndem Wittum ent¬ schlossen, ganz der Erziehung ihrer Kinder widmete.Der junge Prinz war im Gegensatz zu seinen Geschwistern ein häßliches, krankes, nervöses und eigenwilliges Kind.Es hat sich deshalb die Sage gebildet, als ob er von seinen Angehörigen, selbst von seiner Mutter, lieblos behandelt worden sei.Daß dies jedoch keineswegs der Fall war, beweisen unter anderem, hauptsächlich Bruchstücke aus drei Briefen des Augustus, aus denen klar hervorgeht, einmal daß sowohl dem *) Tacitus, ann.I, 1. Flavius Josephus, Jüd-Altert.XX, 8, 3. -') Den Beinamen Germanicus bekam | F20: 1914.0 | G20: 1914-01-01 | I20: UNCERTAIN | J20: LOW | K20: INSUFFICIENT_CONTEXT | L20: Claudius帝研究。表示テキストにJosephusの言及なし（本文で典拠として引用の可能性はある） | M20: OABASEV1_592310b2470b57c2 | N20: W000004772 | O20: W7008987317
A21: 91 | B21: Chaucer | C21: Geoffrey Chaucer | D21: REVIEWS | E21: REVIEWS Get access The Book of Troilus and Criseyde by Geoffrey Chaucer, edited from all the known Manuscripts by ROBERT KILBURN ROOT, Professor of English in Princeton University. London: Oxford University Press. Pp. xc. + 573. 27s. A. J. WYATT A. J. WYATT Search for other works by this author on: Oxford Academic Google Scholar The Review of English Studies, Volume os-III, Issue 10, April 1927, Pages 240–241, https://doi.org/10.1093/res/os-III.10.240 Published: 01 April 1927 | F21: 1927.0 | G21: 1927-01-01 | H21: https://doi.org/10.1093/res/os-iii.10.240 | I21: VALID_TARGET_REFERENCE | J21: HIGH | K21: DIRECT_TARGET_REFERENCE | L21: 著者名ターゲット：Troilus and Criseyde 校訂版の書評 | M21: OABASEV1_a82697efbae9323f | N21: W000005351 | O21: W4256564283
A22: 92 | B22: The Secret Garden | C22: Frances Hodgson Burnett | D22: free book pdf downloads | E22: free book pdf downloads Rating: 4.7 / 5 (4500 votes) Downloads: 23856 = = = = = CLICK HERE TO DOWNLOAD = = = = = Upgrade Premium. All free and available in most ereader formats Looking for free digital books? Best Free PDF eBooks , · An illustration of an open book. Z-Library – Unlock the Power of Knowledge with Zlibrary. LLooking for free digital books? Download books in PDF and many formats for free. Look no further than Z-Library! Welcome to Project Gutenberg. Browse zlibrary vast collection of books today! Lavada Redin what are your favorite comfort books. Audio. Look no further than Z-Library! Video. This online service offers easy access to the NCERT textbooks. Browse zlibrary vast collection of books today! An illustration of two cells of a film strip. All free and available in most ereader formats Looking for free digital books? Download books in PDF and many formats for free. My library Textbooks PDF (I-XII) Welcome to the Online Textbooks Section. Z-Library – Unlock the Power of Knowledge with Zlibrary. For this reason, we have a limit on daily download. Most books are stored in the elastic cloud 1) TheMost Downloaded Free BooksAlternative Therapy BooksAnimal BooksArt & Photography BooksBiology BooksBusiness BooksChemistry InstaPDF is a free online PDF search engine that allows you to look for, preview, and download PDF files or documents. "GONE GIRL" BY GILLIAN FLYNN. Look no further than Z-Library! Upgrade Premium. Choose among free epub and Kindle eBooks, download them or read them online. Welcome to Z Library, your ultimate destination for accessing a vast collection of free eBooks Great selection of modern and classic books waiting to be discovered. An illustration of a " floppy PDF Books World offers free eBooks on fiction, non-fiction, academic, textbooks and childrens categories for download online in high quality PDF format Search the worlds most comprehensive index of full-text books. Project Gutenberg is a library of over, free eBooks. Browse zlibrary vast collection of books today! An illustration of an audio speaker. Most books are stored in the elastic cloud where traffic is expensive. Welcome to Z Library, your ultimate destination for accessing a vast collection of free eBooks Most books are stored in the elastic cloud where traffic is expensive. Choose among free epub and Kindle eBooks, download them or read them online. "THE SECRET GARDEN" BY FRANCES HODGSON BURNETT. Download books in PDF and many formats for free. Project Gutenberg is a library of over, free eBooks. There are often several download options, like EPUB, PDF, AZW3, and FBTheyre also readable online through the sites built-in book reader Welcome to Project Gutenberg. Books. The service covers textbooks of all subjects Great selection of modern and classic books waiting to be discovered. You will find the world's great literature here, with focus on older works for which U.S. copyright has expired Z-Library ProjectDownload Books Free With ZLibrary. Upgrade Premium. Choose among free epub and Kindle eBooks, download them or read them online. You Z-Library ProjectDownload Books Free With ZLibrary. You will find the world's great literature here, with focus on older works for which U.S. copyright has expired Z-Library ProjectDownload Books Free With ZLibrary. Project Gutenberg is a library of over, free eBooks. For this reason, we have a limit on daily download. Downloading books requires a free user account unless theres a link to Amazon, in which case you can grab it with your Amazon account. "THIS IS HOW Welcome to Project Gutenberg. Z-Library – Unlock the Power of Knowledge with Zlibrary. | F22: 2024.0 | G22: 2024-06-10 | H22: https://doi.org/10.5281/zenodo.12495283 | I22: VALID_TARGET_REFERENCE | J22: MEDIUM | K22: VALID_CONTEXTUAL_REFERENCE | L22: スパム的集約テキストだが "THE SECRET GARDEN" BY FRANCES HODGSON BURNETT を明記 | M22: OABASEV1_3d12c3b3cbe5bc1a | N22: W000025226 | O22: W6949343916
A23: 93 | B23: Du côté de chez Swann | C23: Marcel Proust | D23: Du côté de chez Swann de Marcel Proust | F23: 1974.0 | G23: 1974-01-01 | I23: VALID_TARGET_REFERENCE | J23: HIGH | K23: DIRECT_TARGET_REFERENCE | M23: OABASEV1_13aba39e17ce90d5 | N23: W000014533 | O23: W1531705365
A24: 94 | B24: Heart of Darkness | C24: Joseph Conrad | D24: The "Obscure truth" in Joseph Conrad's Heart of darkness and Lord Jim | F24: 1975.0 | G24: 1975-01-01 | I24: VALID_TARGET_REFERENCE | J24: HIGH | K24: DIRECT_TARGET_REFERENCE | M24: OABASEV1_aab98e3da0bd5a0e | N24: W000014830 | O24: W629335683
